{"ts": 1774674602.1352277, "data": {"prevDate": "2025-10-15", "currentDate": "2025-10-16", "nextDate": "2025-10-17", "gameWeek": [{"date": "2025-10-13", "dayAbbrev": "MON", "numberOfGames": 10}, {"date": "2025-10-14", "dayAbbrev": "TUE", "numberOfGames": 8}, {"date": "2025-10-15", "dayAbbrev": "WED", "numberOfGames": 4}, {"date": "2025-10-16", "dayAbbrev": "THU", "numberOfGames": 11}, {"date": "2025-10-17", "dayAbbrev": "FRI", "numberOfGames": 4}, {"date": "2025-10-18", "dayAbbrev": "SAT", "numberOfGames": 13}, {"date": "2025-10-19", "dayAbbrev": "SUN", "numberOfGames": 4}], "oddsPartners": [{"partnerId": 2, "country": "SE", "name": "Unibet", "imageUrl": "https://assets.nhle.com/betting_partner/unibet.svg", "siteUrl": "https://www.unibet.se/betting/sports/filter/ice_hockey/nhl/all/matches", "bgColor": "#14805E", "textColor": "#FFFFFF", "accentColor": "#3AAA35"}, {"partnerId": 3, "country": "CZ", "name": "Tipsport", "imageUrl": "https://assets.nhle.com/betting_partner/tipsport.svg", "siteUrl": "https://www.tipsport.cz/PartnerRedirectAction.do?pid=16961&sid=20360&bid=34954&tid=11268", "bgColor": "#2497F2", "textColor": "#FFFFFF", "accentColor": "#FFFFFF"}, {"partnerId": 6, "country": "FI", "name": "Veikkaus", "imageUrl": "https://assets.nhle.com/betting_partner/veikkaus.svg", "siteUrl": "https://www.veikkaus.fi/fi/vedonlyonti/pitkaveto?t=3-2-1_NHL", "bgColor": "#0025F5", "textColor": "#FFFFFF", "accentColor": "#FFFFFF"}, {"partnerId": 7, "country": "CA", "name": "FanDuel", "imageUrl": "https://assets.nhle.com/betting_partner/fanduel.svg", "siteUrl": "https://fanduel.com", "bgColor": "#0078ff", "textColor": "#FFFFFF", "accentColor": "#FFFFFF"}, {"partnerId": 8, "country": "DE", "name": "Sportradar", "imageUrl": "https://assets.nhle.com/betting_partner/sportsradar.svg", "siteUrl": "https://sportradar.com", "bgColor": "#000000", "textColor": "#FFFFFF", "accentColor": "#E6E6E6"}, {"partnerId": 9, "country": "US", "name": "DraftKings", "imageUrl": "https://assets.nhle.com/betting_partner/draftkings.svg", "siteUrl": "https://dksb.sng.link/As9kz/3i4d?_dl=https%3A%2F%2Fsportsbook.draftkings.com%2Fgateway%3Fs%3D333653091&pcid=427326&psn=1320&pcn=NHL&pscn=OddsWidget&pcrn=NoOffer&pscid=SP&wpcid=427326&wpsrc=1320&wpcn=NHL&wpscn=OddsWidget&wpcrn=NoOffer&wpscid=SP&_forward_params=1", "bgColor": "#000000", "textColor": "#FFFFFF", "accentColor": "#FFFFFF"}, {"partnerId": 10, "country": "SK", "name": "Doxxbet", "imageUrl": "https://assets.nhle.com/betting_partner/doxxbet.svg", "siteUrl": "https://www.doxxbet.sk/sk/sportove-tipovanie-online/kurzy/ladovy-hokej/usa/nhl/?msID=21&mbID=27", "bgColor": "#f30d31", "textColor": "#202020", "accentColor": "#ffffff"}], "games": [{"id": 2025020061, "season": 20252026, "gameType": 2, "gameDate": "2025-10-16", "venue": {"default": "Scotiabank Arena"}, "startTimeUTC": "2025-10-16T23:00:00Z", "easternUTCOffset": "-04:00", "venueUTCOffset": "-04:00", "tvBroadcasts": [{"id": 293, "market": "H", "countryCode": "CA", "network": "TSN4", "sequenceNumber": 137}, {"id": 27, "market": "A", "countryCode": "US", "network": "MSG", "sequenceNumber": 417}], "gameState": "OFF", "gameScheduleState": "OK", "awayTeam": {"id": 3, "name": {"default": "Rangers"}, "abbrev": "NYR", "score": 1, "sog": 29, "logo": "https://assets.nhle.com/logos/nhl/svg/NYR_light.svg"}, "homeTeam": {"id": 10, "name": {"default": "Maple Leafs"}, "abbrev": "TOR", "score": 2, "sog": 24, "logo": "https://assets.nhle.com/logos/nhl/svg/TOR_light.svg"}, "gameCenterLink": "/gamecenter/nyr-vs-tor/2025/10/16/2025020061", "threeMinRecap": "/video/nyr-at-tor-recap-6382872173112", "threeMinRecapFr": "/fr/video/nyr-vs-tor-16-10-2025-resume-6382869603112", "condensedGame": "/video/nyr-at-tor-condensed-game-6382870406112", "condensedGameFr": "/fr/video/match-condense-rangers-maple-leafs-16-10-2025-6382871793112", "clock": {"timeRemaining": "04:02", "secondsRemaining": 242, "running": false, "inIntermission": false}, "neutralSite": false, "venueTimezone": "America/Toronto", "period": 4, "periodDescriptor": {"number": 4, "periodType": "OT", "maxRegulationPeriods": 3}, "gameOutcome": {"lastPeriodType": "OT", "otPeriods": 1}, "goals": [{"period": 1, "periodDescriptor": {"number": 1, "periodType": "REG", "maxRegulationPeriods": 3}, "timeInPeriod": "11:48", "playerId": 8482720, "name": {"default": "M. Knies"}, "firstName": {"default": "Matthew"}, "lastName": {"default": "Knies"}, "goalModifier": "none", "assists": [{"playerId": 8477939, "name": {"default": "W. Nylander"}, "assistsToDate": 6}, {"playerId": 8475171, "name": {"default": "O. Ekman-Larsson"}, "assistsToDate": 3}], "mugshot": "https://assets.nhle.com/mugs/nhl/20252026/TOR/8482720.png", "teamAbbrev": "TOR", "goalsToDate": 2, "awayScore": 0, "homeScore": 1, "strength": "pp", "highlightClipSharingUrl": "https://nhl.com/video/nyr-tor-knies-scores-ppg-against-igor-shesterkin-6382866443112", "highlightClipSharingUrlFr": "https://nhl.com/fr/video/nyr-tor-knies-marque-un-but-en-a-n-contre-igor-shesterkin-6382865864112", "highlightClip": 6382866443112, "highlightClipFr": 6382865864112, "discreteClip": 6382866353112, "discreteClipFr": 6382865172112}, {"period": 3, "periodDescriptor": {"number": 3, "periodType": "REG", "maxRegulationPeriods": 3}, "timeInPeriod": "04:51", "playerId": 8481704, "name": {"default": "J. Parssinen", "cs": "J. P\u00e4rssinen", "fi": "J. P\u00e4rssinen", "sk": "J. P\u00e4rssinen", "sv": "J. P\u00e4rssinen"}, "firstName": {"default": "Juuso"}, "lastName": {"default": "Parssinen", "cs": "P\u00e4rssinen", "fi": "P\u00e4rssinen", "sk": "P\u00e4rssinen", "sv": "P\u00e4rssinen"}, "goalModifier": "none", "assists": [{"playerId": 8482073, "name": {"default": "B. Schneider"}, "assistsToDate": 2}], "mugshot": "https://assets.nhle.com/mugs/nhl/20252026/NYR/8481704.png", "teamAbbrev": "NYR", "goalsToDate": 1, "awayScore": 1, "homeScore": 1, "strength": "ev", "highlightClipSharingUrl": "https://nhl.com/video/nyr-tor-parssinen-scores-goal-against-anthony-stolarz-6382870040112", "highlightClipSharingUrlFr": "https://nhl.com/fr/video/nyr-tor-parssinen-marque-un-but-contre-anthony-stolarz-6382867705112", "highlightClip": 6382870040112, "highlightClipFr": 6382867705112, "discreteClip": 6382868813112, "discreteClipFr": 6382867600112}, {"period": 4, "periodDescriptor": {"number": 4, "periodType": "OT", "maxRegulationPeriods": 3}, "timeInPeriod": "00:58", "playerId": 8479318, "name": {"default": "A. Matthews"}, "firstName": {"default": "Auston"}, "lastName": {"default": "Matthews"}, "goalModifier": "none", "assists": [{"playerId": 8477939, "name": {"default": "W. Nylander"}, "assistsToDate": 7}, {"playerId": 8476853, "name": {"default": "M. Rielly"}, "assistsToDate": 4}], "mugshot": "https://assets.nhle.com/mugs/nhl/20252026/TOR/8479318.png", "teamAbbrev": "TOR", "goalsToDate": 4, "awayScore": 1, "homeScore": 2, "strength": "ev", "highlightClipSharingUrl": "https://nhl.com/video/nyr-tor-matthews-scores-goal-against-igor-shesterkin-6382869721112", "highlightClipSharingUrlFr": "https://nhl.com/fr/video/nyr-tor-matthews-marque-un-but-contre-igor-shesterkin-6382870221112", "highlightClip": 6382869721112, "highlightClipFr": 6382870221112, "discreteClip": 6382870897112, "discreteClipFr": 6382871977112}]}, {"id": 2025020062, "season": 20252026, "gameType": 2, "gameDate": "2025-10-16", "venue": {"default": "Centre Bell"}, "startTimeUTC": "2025-10-16T23:00:00Z", "easternUTCOffset": "-04:00", "venueUTCOffset": "-04:00", "tvBroadcasts": [{"id": 131, "market": "H", "countryCode": "CA", "network": "TSN2", "sequenceNumber": 112}, {"id": 33, "market": "H", "countryCode": "CA", "network": "RDS", "sequenceNumber": 145}, {"id": 561, "market": "A", "countryCode": "US", "network": "FDSNSO", "sequenceNumber": 202}], "gameState": "OFF", "gameScheduleState": "OK", "awayTeam": {"id": 18, "name": {"default": "Predators"}, "abbrev": "NSH", "score": 2, "sog": 19, "logo": "https://assets.nhle.com/logos/nhl/svg/NSH_light.svg"}, "homeTeam": {"id": 8, "name": {"default": "Canadiens"}, "abbrev": "MTL", "score": 3, "sog": 30, "logo": "https://assets.nhle.com/logos/nhl/svg/MTL_light.svg"}, "gameCenterLink": "/gamecenter/nsh-vs-mtl/2025/10/16/2025020062", "threeMinRecap": "/video/nsh-at-mtl-recap-6382870615112", "threeMinRecapFr": "/fr/video/nsh-vs-mtl-16-10-2025-resume-6382871295112", "condensedGame": "/video/nsh-at-mtl-condensed-game-6382871598112", "condensedGameFr": "/fr/video/match-condense-predators-canadiens-16-10-2025-6382870613112", "clock": {"timeRemaining": "00:03", "secondsRemaining": 3, "running": false, "inIntermission": false}, "neutralSite": false, "venueTimezone": "America/Montreal", "period": 4, "periodDescriptor": {"number": 4, "periodType": "OT", "maxRegulationPeriods": 3}, "gameOutcome": {"lastPeriodType": "OT", "otPeriods": 1}, "goals": [{"period": 2, "periodDescriptor": {"number": 2, "periodType": "REG", "maxRegulationPeriods": 3}, "timeInPeriod": "11:36", "playerId": 8474564, "name": {"default": "S. Stamkos"}, "firstName": {"default": "Steven"}, "lastName": {"default": "Stamkos"}, "goalModifier": "none", "assists": [{"playerId": 8474600, "name": {"default": "R. Josi"}, "assistsToDate": 3}, {"playerId": 8482146, "name": {"default": "L. Evangelista"}, "assistsToDate": 3}], "mugshot": "https://assets.nhle.com/mugs/nhl/20252026/NSH/8474564.png", "teamAbbrev": "NSH", "goalsToDate": 1, "awayScore": 1, "homeScore": 0, "strength": "pp", "highlightClipSharingUrl": "https://nhl.com/video/nsh-mtl-stamkos-scores-goal-against-jakub-dobes-6382869229112", "highlightClipSharingUrlFr": "https://nhl.com/fr/video/nsh-mtl-stamkos-marque-un-but-contre-jakub-dobes-6382867873112", "highlightClip": 6382869229112, "highlightClipFr": 6382867873112, "discreteClip": 6382866695112, "discreteClipFr": 6382868266112}, {"period": 3, "periodDescriptor": {"number": 3, "periodType": "REG", "maxRegulationPeriods": 3}, "timeInPeriod": "06:02", "playerId": 8482775, "name": {"default": "O. Kapanen"}, "firstName": {"default": "Oliver"}, "lastName": {"default": "Kapanen"}, "goalModifier": "none", "assists": [{"playerId": 8483457, "name": {"default": "L. Hutson"}, "assistsToDate": 3}, {"playerId": 8482087, "name": {"default": "K. Guhle"}, "assistsToDate": 1}], "mugshot": "https://assets.nhle.com/mugs/nhl/20252026/MTL/8482775.png", "teamAbbrev": "MTL", "goalsToDate": 3, "awayScore": 1, "homeScore": 1, "strength": "ev", "highlightClipSharingUrl": "https://nhl.com/video/nsh-mtl-kapanen-scores-goal-against-juuse-saros-6382867597112", "highlightClipSharingUrlFr": "https://nhl.com/fr/video/nsh-mtl-kapanen-marque-un-but-contre-juuse-saros-6382869073112", "highlightClip": 6382867597112, "highlightClipFr": 6382869073112, "discreteClip": 6382869477112, "discreteClipFr": 6382869366112}, {"period": 3, "periodDescriptor": {"number": 3, "periodType": "REG", "maxRegulationPeriods": 3}, "timeInPeriod": "11:21", "playerId": 8480246, "name": {"default": "N. Perbix"}, "firstName": {"default": "Nick", "cs": "Nicklaus", "de": "Nicklaus", "es": "Nicklaus", "fi": "Nicklaus", "sk": "Nicklaus", "sv": "Nicklaus"}, "lastName": {"default": "Perbix"}, "goalModifier": "none", "assists": [{"playerId": 8477446, "name": {"default": "M. McCarron"}, "assistsToDate": 1}], "mugshot": "https://assets.nhle.com/mugs/nhl/20252026/NSH/8480246.png", "teamAbbrev": "NSH", "goalsToDate": 2, "awayScore": 2, "homeScore": 1, "strength": "ev", "highlightClipSharingUrl": "https://nhl.com/video/nsh-mtl-perbix-scores-goal-against-jakub-dobes-6382870642112", "highlightClipSharingUrlFr": "https://nhl.com/fr/video/nsh-mtl-perbix-marque-un-but-contre-jakub-dobes-6382869268112", "highlightClip": 6382870642112, "highlightClipFr": 6382869268112, "discreteClip": 6382870146112, "discreteClipFr": 6382870047112}, {"period": 3, "periodDescriptor": {"number": 3, "periodType": "REG", "maxRegulationPeriods": 3}, "timeInPeriod": "19:40", "playerId": 8481540, "name": {"default": "C. Caufield"}, "firstName": {"default": "Cole"}, "lastName": {"default": "Caufield"}, "goalModifier": "none", "assists": [{"playerId": 8483457, "name": {"default": "L. Hutson"}, "assistsToDate": 4}], "mugshot": "https://assets.nhle.com/mugs/nhl/20252026/MTL/8481540.png", "teamAbbrev": "MTL", "goalsToDate": 4, "awayScore": 2, "homeScore": 2, "strength": "ev", "highlightClipSharingUrl": "https://nhl.com/video/nsh-mtl-caufield-scores-goal-against-juuse-saros-6382868516112", "highlightClipSharingUrlFr": "https://nhl.com/fr/video/nsh-mtl-caufield-marque-un-but-contre-juuse-saros-6382868012112", "highlightClip": 6382868516112, "highlightClipFr": 6382868012112, "discreteClip": 6382869186112, "discreteClipFr": 6382869185112}, {"period": 4, "periodDescriptor": {"number": 4, "periodType": "OT", "maxRegulationPeriods": 3}, "timeInPeriod": "04:57", "playerId": 8481540, "name": {"default": "C. Caufield"}, "firstName": {"default": "Cole"}, "lastName": {"default": "Caufield"}, "goalModifier": "none", "assists": [{"playerId": 8480018, "name": {"default": "N. Suzuki"}, "assistsToDate": 7}, {"playerId": 8476875, "name": {"default": "M. Matheson"}, "assistsToDate": 3}], "mugshot": "https://assets.nhle.com/mugs/nhl/20252026/MTL/8481540.png", "teamAbbrev": "MTL", "goalsToDate": 5, "awayScore": 2, "homeScore": 3, "strength": "ev", "highlightClipSharingUrl": "https://nhl.com/video/nsh-mtl-caufield-scores-goal-against-juuse-saros-6382869909112", "highlightClipSharingUrlFr": "https://nhl.com/fr/video/nsh-mtl-caufield-marque-un-but-contre-juuse-saros-6382869728112", "highlightClip": 6382869909112, "highlightClipFr": 6382869728112, "discreteClip": 6382870711112, "discreteClipFr": 6382869722112}]}, {"id": 2025020063, "season": 20252026, "gameType": 2, "gameDate": "2025-10-16", "venue": {"default": "Canadian Tire Centre"}, "startTimeUTC": "2025-10-16T23:00:00Z", "easternUTCOffset": "-04:00", "venueUTCOffset": "-04:00", "tvBroadcasts": [{"id": 294, "market": "H", "countryCode": "CA", "network": "TSN5", "sequenceNumber": 135}, {"id": 242, "market": "H", "countryCode": "CA", "network": "RDSI", "sequenceNumber": 147}, {"id": 554, "market": "A", "countryCode": "US", "network": "KHN/Prime", "sequenceNumber": 348}, {"id": 388, "market": "A", "countryCode": "US", "network": "KONG", "sequenceNumber": 654}], "gameState": "OFF", "gameScheduleState": "OK", "awayTeam": {"id": 55, "name": {"default": "Kraken"}, "abbrev": "SEA", "score": 3, "sog": 33, "logo": "https://assets.nhle.com/logos/nhl/svg/SEA_light.svg"}, "homeTeam": {"id": 9, "name": {"default": "Senators", "fr": "S\u00e9nateurs"}, "abbrev": "OTT", "score": 4, "sog": 23, "logo": "https://assets.nhle.com/logos/nhl/svg/OTT_light.svg"}, "gameCenterLink": "/gamecenter/sea-vs-ott/2025/10/16/2025020063", "threeMinRecap": "/video/sea-at-ott-recap-6382871381112", "threeMinRecapFr": "/fr/video/sea-vs-ott-16-10-2025-resume-6382870796112", "condensedGame": "/video/sea-at-ott-condensed-game-6382871805112", "condensedGameFr": "/fr/video/match-condense-kraken-senators-16-10-2025-6382869612112", "clock": {"timeRemaining": "00:00", "secondsRemaining": 0, "running": false, "inIntermission": false}, "neutralSite": false, "venueTimezone": "US/Eastern", "period": 5, "periodDescriptor": {"number": 5, "periodType": "SO", "maxRegulationPeriods": 3}, "gameOutcome": {"lastPeriodType": "SO"}, "goals": [{"period": 1, "periodDescriptor": {"number": 1, "periodType": "REG", "maxRegulationPeriods": 3}, "timeInPeriod": "04:57", "playerId": 8483524, "name": {"default": "S. Wright"}, "firstName": {"default": "Shane"}, "lastName": {"default": "Wright"}, "goalModifier": "none", "assists": [{"playerId": 8477986, "name": {"default": "B. Montour"}, "assistsToDate": 3}, {"playerId": 8478975, "name": {"default": "M. Marchment"}, "assistsToDate": 1}], "mugshot": "https://assets.nhle.com/mugs/nhl/20252026/SEA/8483524.png", "teamAbbrev": "SEA", "goalsToDate": 1, "awayScore": 1, "homeScore": 0, "strength": "ev", "highlightClipSharingUrl": "https://nhl.com/video/sea-ott-wright-scores-goal-against-linus-ullmark-6382866338112", "highlightClipSharingUrlFr": "https://nhl.com/fr/video/sea-ott-wright-marque-un-but-contre-linus-ullmark-6382865152112", "highlightClip": 6382866338112, "highlightClipFr": 6382865152112, "discreteClip": 6382866341112, "discreteClipFr": 6382866630112}, {"period": 1, "periodDescriptor": {"number": 1, "periodType": "REG", "maxRegulationPeriods": 3}, "timeInPeriod": "07:42", "playerId": 8481596, "name": {"default": "S. Pinto"}, "firstName": {"default": "Shane"}, "lastName": {"default": "Pinto"}, "goalModifier": "none", "assists": [{"playerId": 8474189, "name": {"default": "L. Eller"}, "assistsToDate": 1}, {"playerId": 8473512, "name": {"default": "C. Giroux"}, "assistsToDate": 2}], "mugshot": "https://assets.nhle.com/mugs/nhl/20252026/OTT/8481596.png", "teamAbbrev": "OTT", "goalsToDate": 6, "awayScore": 1, "homeScore": 1, "strength": "ev", "highlightClipSharingUrl": "https://nhl.com/video/sea-ott-pinto-scores-goal-against-philipp-grubauer-6382866433112", "highlightClipSharingUrlFr": "https://nhl.com/fr/video/sea-ott-pinto-marque-un-but-contre-philipp-grubauer-6382866534112", "highlightClip": 6382866433112, "highlightClipFr": 6382866534112, "discreteClip": 6382866067112, "discreteClipFr": 6382866731112}, {"period": 1, "periodDescriptor": {"number": 1, "periodType": "REG", "maxRegulationPeriods": 3}, "timeInPeriod": "09:35", "playerId": 8474102, "name": {"default": "D. Perron"}, "firstName": {"default": "David"}, "lastName": {"default": "Perron"}, "goalModifier": "none", "assists": [{"playerId": 8473512, "name": {"default": "C. Giroux"}, "assistsToDate": 3}, {"playerId": 8478469, "name": {"default": "T. Chabot"}, "assistsToDate": 1}], "mugshot": "https://assets.nhle.com/mugs/nhl/20252026/OTT/8474102.png", "teamAbbrev": "OTT", "goalsToDate": 1, "awayScore": 1, "homeScore": 2, "strength": "pp", "highlightClipSharingUrl": "https://nhl.com/video/sea-ott-perron-scores-ppg-against-philipp-grubauer-6382865678112", "highlightClipSharingUrlFr": "https://nhl.com/fr/video/sea-ott-perron-marque-un-but-en-a-n-contre-philipp-grubauer-6382866248112", "highlightClip": 6382865678112, "highlightClipFr": 6382866248112, "discreteClip": 6382866647112, "discreteClipFr": 6382864871112}, {"period": 2, "periodDescriptor": {"number": 2, "periodType": "REG", "maxRegulationPeriods": 3}, "timeInPeriod": "04:40", "playerId": 8476905, "name": {"default": "C. Stephenson"}, "firstName": {"default": "Chandler"}, "lastName": {"default": "Stephenson"}, "goalModifier": "none", "assists": [{"playerId": 8475768, "name": {"default": "J. Schwartz"}, "assistsToDate": 2}], "mugshot": "https://assets.nhle.com/mugs/nhl/20252026/SEA/8476905.png", "teamAbbrev": "SEA", "goalsToDate": 1, "awayScore": 2, "homeScore": 2, "strength": "ev", "highlightClipSharingUrl": "https://nhl.com/video/sea-ott-stephenson-scores-goal-against-linus-ullmark-6382867749112", "highlightClipSharingUrlFr": "https://nhl.com/fr/video/sea-ott-stephenson-marque-un-but-contre-linus-ullmark-6382867647112", "highlightClip": 6382867749112, "highlightClipFr": 6382867647112, "discreteClip": 6382867645112, "discreteClipFr": 6382868923112}, {"period": 3, "periodDescriptor": {"number": 3, "periodType": "REG", "maxRegulationPeriods": 3}, "timeInPeriod": "02:15", "playerId": 8476905, "name": {"default": "C. Stephenson"}, "firstName": {"default": "Chandler"}, "lastName": {"default": "Stephenson"}, "goalModifier": "none", "assists": [{"playerId": 8474586, "name": {"default": "J. Eberle"}, "assistsToDate": 3}, {"playerId": 8477986, "name": {"default": "B. Montour"}, "assistsToDate": 4}], "mugshot": "https://assets.nhle.com/mugs/nhl/20252026/SEA/8476905.png", "teamAbbrev": "SEA", "goalsToDate": 2, "awayScore": 3, "homeScore": 2, "strength": "pp", "highlightClipSharingUrl": "https://nhl.com/video/sea-ott-stephenson-scores-ppg-against-linus-ullmark-6382869649112", "highlightClipSharingUrlFr": "https://nhl.com/fr/video/sea-ott-stephenson-marque-un-but-en-a-n-contre-linus-ullmark-6382868690112", "highlightClip": 6382869649112, "highlightClipFr": 6382868690112, "discreteClip": 6382869552112, "discreteClipFr": 6382869164112}, {"period": 3, "periodDescriptor": {"number": 3, "periodType": "REG", "maxRegulationPeriods": 3}, "timeInPeriod": "18:14", "playerId": 8481528, "name": {"default": "D. Cozens"}, "firstName": {"default": "Dylan"}, "lastName": {"default": "Cozens"}, "goalModifier": "none", "assists": [{"playerId": 8480208, "name": {"default": "D. Batherson"}, "assistsToDate": 1}, {"playerId": 8481606, "name": {"default": "J. Spence"}, "assistsToDate": 4}], "mugshot": "https://assets.nhle.com/mugs/nhl/20252026/OTT/8481528.png", "teamAbbrev": "OTT", "goalsToDate": 2, "awayScore": 3, "homeScore": 3, "strength": "ev", "highlightClipSharingUrl": "https://nhl.com/video/sea-ott-cozens-scores-goal-against-philipp-grubauer-6382870964112", "highlightClipSharingUrlFr": "https://nhl.com/fr/video/sea-ott-cozens-marque-un-but-contre-philipp-grubauer-6382869198112", "highlightClip": 6382870964112, "highlightClipFr": 6382869198112, "discreteClip": 6382870963112, "discreteClipFr": 6382868916112}, {"period": 5, "periodDescriptor": {"number": 5, "periodType": "SO", "maxRegulationPeriods": 3}, "timeInPeriod": "00:00", "playerId": 8482116, "name": {"default": "T. St\u00fctzle"}, "firstName": {"default": "Tim"}, "lastName": {"default": "St\u00fctzle"}, "goalModifier": "none", "assists": [], "mugshot": "https://assets.nhle.com/mugs/nhl/20252026/OTT/8482116.png", "teamAbbrev": "OTT", "awayScore": 3, "homeScore": 4, "strength": "ev"}]}, {"id": 2025020064, "season": 20252026, "gameType": 2, "gameDate": "2025-10-16", "venue": {"default": "Prudential Center"}, "startTimeUTC": "2025-10-16T23:00:00Z", "easternUTCOffset": "-04:00", "venueUTCOffset": "-04:00", "tvBroadcasts": [{"id": 409, "market": "H", "countryCode": "US", "network": "MSGSN", "sequenceNumber": 411}, {"id": 521, "market": "A", "countryCode": "US", "network": "SCRIPPS", "sequenceNumber": 657}], "gameState": "OFF", "gameScheduleState": "OK", "awayTeam": {"id": 13, "name": {"default": "Panthers"}, "abbrev": "FLA", "score": 1, "sog": 22, "logo": "https://assets.nhle.com/logos/nhl/svg/FLA_light.svg"}, "homeTeam": {"id": 1, "name": {"default": "Devils"}, "abbrev": "NJD", "score": 3, "sog": 33, "logo": "https://assets.nhle.com/logos/nhl/svg/NJD_light.svg"}, "gameCenterLink": "/gamecenter/fla-vs-njd/2025/10/16/2025020064", "threeMinRecap": "/video/fla-at-njd-recap-6382871365112", "threeMinRecapFr": "/fr/video/fla-vs-njd-16-10-2025-resume-6382871185112", "condensedGame": "/video/fla-at-njd-condensed-game-6382870589112", "condensedGameFr": "/fr/video/match-condense-panthers-devils-16-10-2025-6382869711112", "clock": {"timeRemaining": "00:00", "secondsRemaining": 0, "running": false, "inIntermission": false}, "neutralSite": false, "venueTimezone": "US/Eastern", "period": 3, "periodDescriptor": {"number": 3, "periodType": "REG", "maxRegulationPeriods": 3}, "gameOutcome": {"lastPeriodType": "REG"}, "goals": [{"period": 1, "periodDescriptor": {"number": 1, "periodType": "REG", "maxRegulationPeriods": 3}, "timeInPeriod": "01:59", "playerId": 8478542, "name": {"default": "E. Rodrigues"}, "firstName": {"default": "Evan"}, "lastName": {"default": "Rodrigues"}, "goalModifier": "none", "assists": [{"playerId": 8473419, "name": {"default": "B. Marchand"}, "assistsToDate": 3}, {"playerId": 8477495, "name": {"default": "S. Jones"}, "assistsToDate": 3}], "mugshot": "https://assets.nhle.com/mugs/nhl/20252026/FLA/8478542.png", "teamAbbrev": "FLA", "goalsToDate": 2, "awayScore": 1, "homeScore": 0, "strength": "ev", "highlightClipSharingUrl": "https://nhl.com/video/fla-njd-rodrigues-scores-goal-against-jake-allen-6382864780112", "highlightClipSharingUrlFr": "https://nhl.com/fr/video/fla-njd-rodrigues-marque-un-but-contre-jake-allen-6382864566112", "highlightClip": 6382864780112, "highlightClipFr": 6382864566112, "discreteClip": 6382866429112, "discreteClipFr": 6382864778112}, {"period": 2, "periodDescriptor": {"number": 2, "periodType": "REG", "maxRegulationPeriods": 3}, "timeInPeriod": "05:48", "playerId": 8481559, "name": {"default": "J. Hughes"}, "firstName": {"default": "Jack"}, "lastName": {"default": "Hughes"}, "goalModifier": "none", "assists": [{"playerId": 8479407, "name": {"default": "J. Bratt"}, "assistsToDate": 3}, {"playerId": 8478414, "name": {"default": "T. Meier"}, "assistsToDate": 2}], "mugshot": "https://assets.nhle.com/mugs/nhl/20252026/NJD/8481559.png", "teamAbbrev": "NJD", "goalsToDate": 1, "awayScore": 1, "homeScore": 1, "strength": "pp", "highlightClipSharingUrl": "https://nhl.com/video/fla-njd-hughes-scores-ppg-against-daniil-tarasov-6382867163112", "highlightClipSharingUrlFr": "https://nhl.com/fr/video/fla-njd-hughes-marque-un-but-en-a-n-contre-daniil-tarasov-6382868543112", "highlightClip": 6382867163112, "highlightClipFr": 6382868543112, "discreteClip": 6382868753112, "discreteClipFr": 6382868063112}, {"period": 3, "periodDescriptor": {"number": 3, "periodType": "REG", "maxRegulationPeriods": 3}, "timeInPeriod": "06:23", "playerId": 8478414, "name": {"default": "T. Meier"}, "firstName": {"default": "Timo"}, "lastName": {"default": "Meier"}, "goalModifier": "none", "assists": [{"playerId": 8483495, "name": {"default": "S. Nemec", "cs": "\u0160. Nemec", "sk": "\u0160. Nemec"}, "assistsToDate": 2}, {"playerId": 8475455, "name": {"default": "B. Dillon"}, "assistsToDate": 2}], "mugshot": "https://assets.nhle.com/mugs/nhl/20252026/NJD/8478414.png", "teamAbbrev": "NJD", "goalsToDate": 3, "awayScore": 1, "homeScore": 2, "strength": "ev", "highlightClipSharingUrl": "https://nhl.com/video/fla-njd-meier-scores-goal-against-daniil-tarasov-6382869752112", "highlightClipSharingUrlFr": "https://nhl.com/fr/video/fla-njd-meier-marque-un-but-contre-daniil-tarasov-6382869658112", "highlightClip": 6382869752112, "highlightClipFr": 6382869658112, "discreteClip": 6382870049112, "discreteClipFr": 6382869080112}, {"period": 3, "periodDescriptor": {"number": 3, "periodType": "REG", "maxRegulationPeriods": 3}, "timeInPeriod": "11:47", "playerId": 8480002, "name": {"default": "N. Hischier"}, "firstName": {"default": "Nico"}, "lastName": {"default": "Hischier"}, "goalModifier": "none", "assists": [{"playerId": 8482110, "name": {"default": "D. Mercer"}, "assistsToDate": 2}], "mugshot": "https://assets.nhle.com/mugs/nhl/20252026/NJD/8480002.png", "teamAbbrev": "NJD", "goalsToDate": 2, "awayScore": 1, "homeScore": 3, "strength": "ev", "highlightClipSharingUrl": "https://nhl.com/video/fla-njd-hischier-scores-goal-against-daniil-tarasov-6382870066112", "highlightClipSharingUrlFr": "https://nhl.com/fr/video/fla-njd-hischier-marque-un-but-contre-daniil-tarasov-6382869569112", "highlightClip": 6382870066112, "highlightClipFr": 6382869569112, "discreteClip": 6382871148112, "discreteClipFr": 6382870251112}]}, {"id": 2025020066, "season": 20252026, "gameType": 2, "gameDate": "2025-10-16", "venue": {"default": "Xfinity Mobile Arena"}, "startTimeUTC": "2025-10-16T23:00:00Z", "easternUTCOffset": "-04:00", "venueUTCOffset": "-04:00", "tvBroadcasts": [{"id": 292, "market": "A", "countryCode": "CA", "network": "TSN3", "sequenceNumber": 134}, {"id": 322, "market": "H", "countryCode": "US", "network": "NBCSP", "sequenceNumber": 389}], "gameState": "OFF", "gameScheduleState": "OK", "awayTeam": {"id": 52, "name": {"default": "Jets"}, "abbrev": "WPG", "score": 5, "sog": 15, "logo": "https://assets.nhle.com/logos/nhl/svg/WPG_light.svg"}, "homeTeam": {"id": 4, "name": {"default": "Flyers"}, "abbrev": "PHI", "score": 2, "sog": 17, "logo": "https://assets.nhle.com/logos/nhl/svg/PHI_light.svg"}, "gameCenterLink": "/gamecenter/wpg-vs-phi/2025/10/16/2025020066", "threeMinRecap": "/video/wpg-at-phi-recap-6382871181112", "threeMinRecapFr": "/fr/video/wpg-vs-phi-16-10-2025-resume-6382869309112", "condensedGame": "/video/wpg-at-phi-condensed-game-6382871476112", "condensedGameFr": "/fr/video/match-condense-jets-flyers-16-10-2025-6382871757112", "clock": {"timeRemaining": "00:00", "secondsRemaining": 0, "running": false, "inIntermission": false}, "neutralSite": false, "venueTimezone": "US/Eastern", "period": 3, "periodDescriptor": {"number": 3, "periodType": "REG", "maxRegulationPeriods": 3}, "gameOutcome": {"lastPeriodType": "REG"}, "goals": [{"period": 1, "periodDescriptor": {"number": 1, "periodType": "REG", "maxRegulationPeriods": 3}, "timeInPeriod": "05:45", "playerId": 8476480, "name": {"default": "V. Namestnikov", "cs": "V. Nam\u011bstnikov"}, "firstName": {"default": "Vladislav"}, "lastName": {"default": "Namestnikov", "cs": "Nam\u011bstnikov"}, "goalModifier": "none", "assists": [{"playerId": 8475799, "name": {"default": "N. Niederreiter"}, "assistsToDate": 2}, {"playerId": 8474679, "name": {"default": "G. Nyquist"}, "assistsToDate": 2}], "mugshot": "https://assets.nhle.com/mugs/nhl/20252026/WPG/8476480.png", "teamAbbrev": "WPG", "goalsToDate": 1, "awayScore": 1, "homeScore": 0, "strength": "ev", "highlightClipSharingUrl": "https://nhl.com/video/wpg-phi-namestnikov-scores-goal-against-samuel-ersson-6382867417112", "highlightClipSharingUrlFr": "https://nhl.com/fr/video/wpg-phi-namestnikov-marque-un-but-contre-samuel-ersson-6382866348112", "highlightClip": 6382867417112, "highlightClipFr": 6382866348112, "discreteClip": 6382867239112, "discreteClipFr": 6382866068112}, {"period": 2, "periodDescriptor": {"number": 2, "periodType": "REG", "maxRegulationPeriods": 3}, "timeInPeriod": "07:01", "playerId": 8476460, "name": {"default": "M. Scheifele"}, "firstName": {"default": "Mark"}, "lastName": {"default": "Scheifele"}, "goalModifier": "none", "assists": [{"playerId": 8480014, "name": {"default": "G. Vilardi"}, "assistsToDate": 4}], "mugshot": "https://assets.nhle.com/mugs/nhl/20252026/WPG/8476460.png", "teamAbbrev": "WPG", "goalsToDate": 4, "awayScore": 2, "homeScore": 0, "strength": "ev", "highlightClipSharingUrl": "https://nhl.com/video/wpg-phi-scheifele-scores-goal-against-samuel-ersson-6382868148112", "highlightClipSharingUrlFr": "https://nhl.com/fr/video/wpg-phi-scheifele-marque-un-but-contre-samuel-ersson-6382867560112", "highlightClip": 6382868148112, "highlightClipFr": 6382867560112, "discreteClip": 6382866774112, "discreteClipFr": 6382867872112}, {"period": 2, "periodDescriptor": {"number": 2, "periodType": "REG", "maxRegulationPeriods": 3}, "timeInPeriod": "16:22", "playerId": 8480015, "name": {"default": "O. Tippett"}, "firstName": {"default": "Owen"}, "lastName": {"default": "Tippett"}, "goalModifier": "none", "assists": [{"playerId": 8481533, "name": {"default": "T. Zegras"}, "assistsToDate": 3}, {"playerId": 8477948, "name": {"default": "T. Sanheim"}, "assistsToDate": 3}], "mugshot": "https://assets.nhle.com/mugs/nhl/20252026/PHI/8480015.png", "teamAbbrev": "PHI", "goalsToDate": 2, "awayScore": 2, "homeScore": 1, "strength": "ev", "highlightClipSharingUrl": "https://nhl.com/video/wpg-phi-tippett-scores-goal-against-connor-hellebuyck-6382866996112", "highlightClipSharingUrlFr": "https://nhl.com/fr/video/wpg-phi-tippett-marque-un-but-contre-connor-hellebuyck-6382868284112", "highlightClip": 6382866996112, "highlightClipFr": 6382868284112, "discreteClip": 6382866794112, "discreteClipFr": 6382869631112}, {"period": 2, "periodDescriptor": {"number": 2, "periodType": "REG", "maxRegulationPeriods": 3}, "timeInPeriod": "17:43", "playerId": 8480289, "name": {"default": "M. Barron"}, "firstName": {"default": "Morgan"}, "lastName": {"default": "Barron"}, "goalModifier": "none", "assists": [{"playerId": 8478398, "name": {"default": "K. Connor"}, "assistsToDate": 3}], "mugshot": "https://assets.nhle.com/mugs/nhl/20252026/WPG/8480289.png", "teamAbbrev": "WPG", "goalsToDate": 3, "awayScore": 3, "homeScore": 1, "strength": "ev", "highlightClipSharingUrl": "https://nhl.com/video/wpg-phi-barron-scores-goal-against-samuel-ersson-6382869350112", "highlightClipSharingUrlFr": "https://nhl.com/fr/video/wpg-phi-barron-marque-un-but-contre-samuel-ersson-6382867973112", "highlightClip": 6382869350112, "highlightClipFr": 6382867973112, "discreteClip": 6382867188112, "discreteClipFr": 6382869244112}, {"period": 3, "periodDescriptor": {"number": 3, "periodType": "REG", "maxRegulationPeriods": 3}, "timeInPeriod": "09:40", "playerId": 8476460, "name": {"default": "M. Scheifele"}, "firstName": {"default": "Mark"}, "lastName": {"default": "Scheifele"}, "goalModifier": "none", "assists": [{"playerId": 8478398, "name": {"default": "K. Connor"}, "assistsToDate": 4}, {"playerId": 8480113, "name": {"default": "A. Iafallo"}, "assistsToDate": 1}], "mugshot": "https://assets.nhle.com/mugs/nhl/20252026/WPG/8476460.png", "teamAbbrev": "WPG", "goalsToDate": 5, "awayScore": 4, "homeScore": 1, "strength": "pp", "highlightClipSharingUrl": "https://nhl.com/video/wpg-phi-scheifele-scores-ppg-against-samuel-ersson-6382870847112", "highlightClipSharingUrlFr": "https://nhl.com/fr/video/mark-scheifele-with-a-powerplay-goal-vs-les-flyers-de-philadelphie-6382869179112", "highlightClip": 6382870847112, "highlightClipFr": 6382869179112, "discreteClip": 6382871047112, "discreteClipFr": 6382870247112}, {"period": 3, "periodDescriptor": {"number": 3, "periodType": "REG", "maxRegulationPeriods": 3}, "timeInPeriod": "17:39", "playerId": 8484387, "name": {"default": "M. Michkov", "cs": "M. Mi\u010dkov", "fi": "M. Mitshkov", "sk": "M. Mi\u010dkov"}, "firstName": {"default": "Matvei", "cs": "Matvej", "sk": "Matvej"}, "lastName": {"default": "Michkov", "cs": "Mi\u010dkov", "fi": "Mitshkov", "sk": "Mi\u010dkov"}, "goalModifier": "none", "assists": [{"playerId": 8478454, "name": {"default": "N. Juulsen"}, "assistsToDate": 1}, {"playerId": 8476461, "name": {"default": "S. Couturier"}, "assistsToDate": 3}], "mugshot": "https://assets.nhle.com/mugs/nhl/20252026/PHI/8484387.png", "teamAbbrev": "PHI", "goalsToDate": 1, "awayScore": 4, "homeScore": 2, "strength": "ev", "highlightClipSharingUrl": "https://nhl.com/video/wpg-phi-michkov-scores-goal-against-connor-hellebuyck-6382869683112", "highlightClipSharingUrlFr": "https://nhl.com/fr/video/wpg-phi-michkov-marque-un-but-contre-connor-hellebuyck-6382869776112", "highlightClip": 6382869683112, "highlightClipFr": 6382869776112, "discreteClip": 6382869008112, "discreteClipFr": 6382870757112}, {"period": 3, "periodDescriptor": {"number": 3, "periodType": "REG", "maxRegulationPeriods": 3}, "timeInPeriod": "18:47", "playerId": 8476871, "name": {"default": "T. Pearson"}, "firstName": {"default": "Tanner"}, "lastName": {"default": "Pearson"}, "goalModifier": "empty-net", "assists": [], "mugshot": "https://assets.nhle.com/mugs/nhl/20252026/WPG/8476871.png", "teamAbbrev": "WPG", "goalsToDate": 2, "awayScore": 5, "homeScore": 2, "strength": "ev", "highlightClipSharingUrl": "https://nhl.com/video/wpg-phi-pearson-scores-empty-net-goal-6382869209112", "highlightClipSharingUrlFr": "https://nhl.com/fr/video/wpg-phi-pearson-wpg-marque-un-but-dans-un-filet-desert-6382871352112", "highlightClip": 6382869209112, "highlightClipFr": 6382871352112, "discreteClip": 6382871163112, "discreteClipFr": 6382869782112}]}, {"id": 2025020067, "season": 20252026, "gameType": 2, "gameDate": "2025-10-16", "venue": {"default": "Nationwide Arena"}, "startTimeUTC": "2025-10-16T23:00:00Z", "easternUTCOffset": "-04:00", "venueUTCOffset": "-04:00", "tvBroadcasts": [{"id": 565, "market": "H", "countryCode": "US", "network": "FDSNOH", "sequenceNumber": 286}, {"id": 2, "market": "A", "countryCode": "US", "network": "ALT", "sequenceNumber": 385}], "gameState": "OFF", "gameScheduleState": "OK", "awayTeam": {"id": 21, "name": {"default": "Avalanche"}, "abbrev": "COL", "score": 4, "sog": 36, "logo": "https://assets.nhle.com/logos/nhl/svg/COL_light.svg"}, "homeTeam": {"id": 29, "name": {"default": "Blue Jackets"}, "abbrev": "CBJ", "score": 1, "sog": 23, "logo": "https://assets.nhle.com/logos/nhl/svg/CBJ_light.svg"}, "gameCenterLink": "/gamecenter/col-vs-cbj/2025/10/16/2025020067", "threeMinRecap": "/video/col-at-cbj-recap-6382870685112", "threeMinRecapFr": "/fr/video/col-vs-cbj-16-10-2025-resume-6382869886112", "condensedGame": "/video/col-at-cbj-condensed-game-6382869317112", "condensedGameFr": "/fr/video/match-condense-avalanche-blue-jackets-16-10-2025-6382869220112", "clock": {"timeRemaining": "00:00", "secondsRemaining": 0, "running": false, "inIntermission": false}, "neutralSite": false, "venueTimezone": "US/Eastern", "period": 3, "periodDescriptor": {"number": 3, "periodType": "REG", "maxRegulationPeriods": 3}, "gameOutcome": {"lastPeriodType": "REG"}, "goals": [{"period": 2, "periodDescriptor": {"number": 2, "periodType": "REG", "maxRegulationPeriods": 3}, "timeInPeriod": "01:36", "playerId": 8478500, "name": {"default": "I. Provorov"}, "firstName": {"default": "Ivan"}, "lastName": {"default": "Provorov"}, "goalModifier": "none", "assists": [{"playerId": 8480893, "name": {"default": "K. Marchenko", "cs": "K. Mar\u010denko", "fi": "K. Martshenko", "sk": "K. Mar\u010denko"}, "assistsToDate": 1}], "mugshot": "https://assets.nhle.com/mugs/nhl/20252026/CBJ/8478500.png", "teamAbbrev": "CBJ", "goalsToDate": 1, "awayScore": 0, "homeScore": 1, "strength": "ev", "highlightClipSharingUrl": "https://nhl.com/video/col-cbj-provorov-scores-goal-against-scott-wedgewood-6382868922112", "highlightClipSharingUrlFr": "https://nhl.com/fr/video/col-cbj-provorov-marque-un-but-contre-scott-wedgewood-6382868137112", "highlightClip": 6382868922112, "highlightClipFr": 6382868137112, "discreteClip": 6382866966112, "discreteClipFr": 6382867070112}, {"period": 2, "periodDescriptor": {"number": 2, "periodType": "REG", "maxRegulationPeriods": 3}, "timeInPeriod": "10:34", "playerId": 8480069, "name": {"default": "C. Makar"}, "firstName": {"default": "Cale"}, "lastName": {"default": "Makar"}, "goalModifier": "none", "assists": [{"playerId": 8480039, "name": {"default": "M. Necas", "cs": "M. Ne\u010das", "sk": "M. Ne\u010das"}, "assistsToDate": 6}, {"playerId": 8477476, "name": {"default": "A. Lehkonen"}, "assistsToDate": 2}], "mugshot": "https://assets.nhle.com/mugs/nhl/20252026/COL/8480069.png", "teamAbbrev": "COL", "goalsToDate": 2, "awayScore": 1, "homeScore": 1, "strength": "ev", "highlightClipSharingUrl": "https://nhl.com/video/col-cbj-makar-scores-goal-against-elvis-merzlikins-6382868450112", "highlightClipSharingUrlFr": "https://nhl.com/fr/video/col-cbj-makar-marque-un-but-contre-elvis-merzlikins-6382868449112", "highlightClip": 6382868450112, "highlightClipFr": 6382868449112, "discreteClip": 6382866697112, "discreteClipFr": 6382867659112}, {"period": 2, "periodDescriptor": {"number": 2, "periodType": "REG", "maxRegulationPeriods": 3}, "timeInPeriod": "11:46", "playerId": 8475754, "name": {"default": "B. Nelson"}, "firstName": {"default": "Brock"}, "lastName": {"default": "Nelson"}, "goalModifier": "none", "assists": [{"playerId": 8470613, "name": {"default": "B. Burns"}, "assistsToDate": 3}, {"playerId": 8476312, "name": {"default": "J. Manson"}, "assistsToDate": 1}], "mugshot": "https://assets.nhle.com/mugs/nhl/20252026/COL/8475754.png", "teamAbbrev": "COL", "goalsToDate": 1, "awayScore": 2, "homeScore": 1, "strength": "ev", "highlightClipSharingUrl": "https://nhl.com/video/col-cbj-nelson-scores-goal-against-elvis-merzlikins-6382867094112", "highlightClipSharingUrlFr": "https://nhl.com/fr/video/col-cbj-nelson-marque-un-but-contre-elvis-merzlikins-6382868657112", "highlightClip": 6382867094112, "highlightClipFr": 6382868657112, "discreteClip": 6382868154112, "discreteClipFr": 6382868652112}, {"period": 2, "periodDescriptor": {"number": 2, "periodType": "REG", "maxRegulationPeriods": 3}, "timeInPeriod": "19:56", "playerId": 8477501, "name": {"default": "V. Nichushkin", "cs": "V. Ni\u010du\u0161kin", "fi": "V. Nitshushkin", "sk": "V. Ni\u010du\u0161kin"}, "firstName": {"default": "Valeri", "cs": "Valerij", "sk": "Valerij"}, "lastName": {"default": "Nichushkin", "cs": "Ni\u010du\u0161kin", "fi": "Nitshushkin", "sk": "Ni\u010du\u0161kin"}, "goalModifier": "none", "assists": [{"playerId": 8484258, "name": {"default": "S. Malinski"}, "assistsToDate": 2}, {"playerId": 8478109, "name": {"default": "V. Olofsson"}, "assistsToDate": 3}], "mugshot": "https://assets.nhle.com/mugs/nhl/20252026/COL/8477501.png", "teamAbbrev": "COL", "goalsToDate": 1, "awayScore": 3, "homeScore": 1, "strength": "ev", "highlightClipSharingUrl": "https://nhl.com/video/col-cbj-nichushkin-scores-goal-against-elvis-merzlikins-6382866798112", "highlightClipSharingUrlFr": "https://nhl.com/fr/video/col-cbj-nichushkin-marque-un-but-contre-elvis-merzlikins-6382868291112", "highlightClip": 6382866798112, "highlightClipFr": 6382868291112, "discreteClip": 6382867680112, "discreteClipFr": 6382867971112}, {"period": 3, "periodDescriptor": {"number": 3, "periodType": "REG", "maxRegulationPeriods": 3}, "timeInPeriod": "18:07", "playerId": 8477501, "name": {"default": "V. Nichushkin", "cs": "V. Ni\u010du\u0161kin", "fi": "V. Nitshushkin", "sk": "V. Ni\u010du\u0161kin"}, "firstName": {"default": "Valeri", "cs": "Valerij", "sk": "Valerij"}, "lastName": {"default": "Nichushkin", "cs": "Ni\u010du\u0161kin", "fi": "Nitshushkin", "sk": "Ni\u010du\u0161kin"}, "goalModifier": "empty-net", "assists": [{"playerId": 8476455, "name": {"default": "G. Landeskog"}, "assistsToDate": 1}, {"playerId": 8480069, "name": {"default": "C. Makar"}, "assistsToDate": 5}], "mugshot": "https://assets.nhle.com/mugs/nhl/20252026/COL/8477501.png", "teamAbbrev": "COL", "goalsToDate": 2, "awayScore": 4, "homeScore": 1, "strength": "ev", "highlightClipSharingUrl": "https://nhl.com/video/col-cbj-nichushkin-scores-empty-net-goal-6382869122112", "highlightClipSharingUrlFr": "https://nhl.com/fr/video/col-cbj-nichushkin-col-marque-un-but-dans-un-filet-desert-6382869881112", "highlightClip": 6382869122112, "highlightClipFr": 6382869881112, "discreteClip": 6382869580112, "discreteClipFr": 6382869991112}]}, {"id": 2025020065, "season": 20252026, "gameType": 2, "gameDate": "2025-10-16", "venue": {"default": "UBS Arena"}, "startTimeUTC": "2025-10-16T23:30:00Z", "easternUTCOffset": "-04:00", "venueUTCOffset": "-04:00", "tvBroadcasts": [{"id": 329, "market": "N", "countryCode": "US", "network": "ESPN+", "sequenceNumber": 16}, {"id": 391, "market": "N", "countryCode": "US", "network": "HULU", "sequenceNumber": 17}, {"id": 283, "market": "N", "countryCode": "CA", "network": "SN360", "sequenceNumber": 114}], "gameState": "OFF", "gameScheduleState": "OK", "awayTeam": {"id": 22, "name": {"default": "Oilers"}, "abbrev": "EDM", "score": 2, "sog": 33, "logo": "https://assets.nhle.com/logos/nhl/svg/EDM_light.svg"}, "homeTeam": {"id": 2, "name": {"default": "Islanders"}, "abbrev": "NYI", "score": 4, "sog": 25, "logo": "https://assets.nhle.com/logos/nhl/svg/NYI_light.svg"}, "gameCenterLink": "/gamecenter/edm-vs-nyi/2025/10/16/2025020065", "threeMinRecap": "/video/edm-at-nyi-recap-6382869830112", "threeMinRecapFr": "/fr/video/edm-vs-nyi-16-10-2025-resume-6382870416112", "condensedGame": "/video/edm-at-nyi-condensed-game-6382872002112", "condensedGameFr": "/fr/video/match-condense-oilers-islanders-16-10-2025-6382871516112", "clock": {"timeRemaining": "00:00", "secondsRemaining": 0, "running": false, "inIntermission": false}, "neutralSite": false, "venueTimezone": "America/New_York", "period": 3, "periodDescriptor": {"number": 3, "periodType": "REG", "maxRegulationPeriods": 3}, "gameOutcome": {"lastPeriodType": "REG"}, "goals": [{"period": 1, "periodDescriptor": {"number": 1, "periodType": "REG", "maxRegulationPeriods": 3}, "timeInPeriod": "16:23", "playerId": 8478445, "name": {"default": "M. Barzal"}, "firstName": {"default": "Mathew"}, "lastName": {"default": "Barzal"}, "goalModifier": "none", "assists": [], "mugshot": "https://assets.nhle.com/mugs/nhl/20252026/NYI/8478445.png", "teamAbbrev": "NYI", "goalsToDate": 1, "awayScore": 0, "homeScore": 1, "strength": "ev", "highlightClipSharingUrl": "https://nhl.com/video/edm-nyi-barzal-scores-goal-against-stuart-skinner-6382866860112", "highlightClipSharingUrlFr": "https://nhl.com/fr/video/edm-nyi-barzal-marque-un-but-contre-stuart-skinner-6382867448112", "highlightClip": 6382866860112, "highlightClipFr": 6382867448112, "discreteClip": 6382866478112, "discreteClipFr": 6382866189112}, {"period": 1, "periodDescriptor": {"number": 1, "periodType": "REG", "maxRegulationPeriods": 3}, "timeInPeriod": "17:40", "playerId": 8477934, "name": {"default": "L. Draisaitl"}, "firstName": {"default": "Leon"}, "lastName": {"default": "Draisaitl"}, "goalModifier": "none", "assists": [{"playerId": 8478402, "name": {"default": "C. McDavid"}, "assistsToDate": 5}, {"playerId": 8485493, "name": {"default": "D. Tomasek"}, "assistsToDate": 2}], "mugshot": "https://assets.nhle.com/mugs/nhl/20252026/EDM/8477934.png", "teamAbbrev": "EDM", "goalsToDate": 3, "awayScore": 1, "homeScore": 1, "strength": "pp", "highlightClipSharingUrl": "https://nhl.com/video/edm-nyi-draisaitl-scores-ppg-against-david-rittich-6382868633112", "highlightClipSharingUrlFr": "https://nhl.com/fr/video/edm-nyi-draisaitl-marque-un-but-en-a-n-contre-david-rittich-6382868347112", "highlightClip": 6382868633112, "highlightClipFr": 6382868347112, "discreteClip": 6382868051112, "discreteClipFr": 6382867748112}, {"period": 2, "periodDescriptor": {"number": 2, "periodType": "REG", "maxRegulationPeriods": 3}, "timeInPeriod": "08:53", "playerId": 8476454, "name": {"default": "R. Nugent-Hopkins"}, "firstName": {"default": "Ryan"}, "lastName": {"default": "Nugent-Hopkins"}, "goalModifier": "none", "assists": [{"playerId": 8480834, "name": {"default": "T. Emberson"}, "assistsToDate": 1}], "mugshot": "https://assets.nhle.com/mugs/nhl/20252026/EDM/8476454.png", "teamAbbrev": "EDM", "goalsToDate": 2, "awayScore": 2, "homeScore": 1, "strength": "ev", "highlightClipSharingUrl": "https://nhl.com/video/edm-nyi-nugent-hopkins-scores-goal-against-david-rittich-6382869251112", "highlightClipSharingUrlFr": "https://nhl.com/fr/video/edm-nyi-nugent-hopkins-marque-un-but-contre-david-rittich-6382869456112", "highlightClip": 6382869251112, "highlightClipFr": 6382869456112, "discreteClip": 6382867388112, "discreteClipFr": 6382868107112}, {"period": 2, "periodDescriptor": {"number": 2, "periodType": "REG", "maxRegulationPeriods": 3}, "timeInPeriod": "17:56", "playerId": 8477500, "name": {"default": "B. Horvat"}, "firstName": {"default": "Bo"}, "lastName": {"default": "Horvat"}, "goalModifier": "none", "assists": [{"playerId": 8476419, "name": {"default": "J. Pageau"}, "assistsToDate": 1}, {"playerId": 8477506, "name": {"default": "R. Pulock"}, "assistsToDate": 1}], "mugshot": "https://assets.nhle.com/mugs/nhl/20252026/NYI/8477500.png", "teamAbbrev": "NYI", "goalsToDate": 1, "awayScore": 2, "homeScore": 2, "strength": "sh", "highlightClipSharingUrl": "https://nhl.com/video/edm-nyi-horvat-scores-shg-against-stuart-skinner-6382869949112", "highlightClipSharingUrlFr": "https://nhl.com/fr/video/edm-nyi-horvat-marque-un-but-en-i-n-contre-stuart-skinner-6382867403112", "highlightClip": 6382869949112, "highlightClipFr": 6382867403112, "discreteClip": 6382868890112, "discreteClipFr": 6382869479112}, {"period": 3, "periodDescriptor": {"number": 3, "periodType": "REG", "maxRegulationPeriods": 3}, "timeInPeriod": "15:14", "playerId": 8477500, "name": {"default": "B. Horvat"}, "firstName": {"default": "Bo"}, "lastName": {"default": "Horvat"}, "goalModifier": "none", "assists": [{"playerId": 8478445, "name": {"default": "M. Barzal"}, "assistsToDate": 2}, {"playerId": 8485366, "name": {"default": "M. Schaefer"}, "assistsToDate": 3}], "mugshot": "https://assets.nhle.com/mugs/nhl/20252026/NYI/8477500.png", "teamAbbrev": "NYI", "goalsToDate": 2, "awayScore": 2, "homeScore": 3, "strength": "pp", "highlightClipSharingUrl": "https://nhl.com/video/edm-nyi-horvat-scores-ppg-against-stuart-skinner-6382870398112", "highlightClipSharingUrlFr": "https://nhl.com/fr/video/edm-nyi-horvat-marque-un-but-en-a-n-contre-stuart-skinner-6382870298112", "highlightClip": 6382870398112, "highlightClipFr": 6382870298112, "discreteClip": 6382871083112, "discreteClipFr": 6382871192112}, {"period": 3, "periodDescriptor": {"number": 3, "periodType": "REG", "maxRegulationPeriods": 3}, "timeInPeriod": "19:51", "playerId": 8477500, "name": {"default": "B. Horvat"}, "firstName": {"default": "Bo"}, "lastName": {"default": "Horvat"}, "goalModifier": "empty-net", "assists": [{"playerId": 8477494, "name": {"default": "J. Drouin"}, "assistsToDate": 2}, {"playerId": 8482476, "name": {"default": "E. Heineman"}, "assistsToDate": 1}], "mugshot": "https://assets.nhle.com/mugs/nhl/20252026/NYI/8477500.png", "teamAbbrev": "NYI", "goalsToDate": 3, "awayScore": 2, "homeScore": 4, "strength": "ev", "highlightClipSharingUrl": "https://nhl.com/video/edm-nyi-horvat-scores-empty-net-goal-6382870231112", "highlightClipSharingUrlFr": "https://nhl.com/fr/video/edm-nyi-horvat-nyi-marque-un-but-dans-un-filet-desert-6382871205112", "highlightClip": 6382870231112, "highlightClipFr": 6382871205112, "discreteClip": 6382872180112, "discreteClipFr": 6382870230112}]}, {"id": 2025020068, "season": 20252026, "gameType": 2, "gameDate": "2025-10-16", "venue": {"default": "American Airlines Center"}, "startTimeUTC": "2025-10-17T00:00:00Z", "easternUTCOffset": "-04:00", "venueUTCOffset": "-05:00", "tvBroadcasts": [{"id": 284, "market": "N", "countryCode": "CA", "network": "SN1", "sequenceNumber": 113}, {"id": 553, "market": "H", "countryCode": "US", "network": "Victory+", "sequenceNumber": 382}], "gameState": "OFF", "gameScheduleState": "OK", "awayTeam": {"id": 23, "name": {"default": "Canucks"}, "abbrev": "VAN", "score": 5, "sog": 26, "logo": "https://assets.nhle.com/logos/nhl/svg/VAN_light.svg"}, "homeTeam": {"id": 25, "name": {"default": "Stars"}, "abbrev": "DAL", "score": 3, "sog": 31, "logo": "https://assets.nhle.com/logos/nhl/svg/DAL_light.svg"}, "gameCenterLink": "/gamecenter/van-vs-dal/2025/10/16/2025020068", "threeMinRecap": "/video/van-at-dal-recap-6382871319112", "threeMinRecapFr": "/fr/video/van-vs-dal-16-10-2025-resume-6382872217112", "condensedGame": "/video/van-at-dal-condensed-game-6382871638112", "condensedGameFr": "/fr/video/match-condense-canucks-stars-16-10-2025-6382872976112", "clock": {"timeRemaining": "00:00", "secondsRemaining": 0, "running": true, "inIntermission": false}, "neutralSite": false, "venueTimezone": "US/Central", "period": 3, "periodDescriptor": {"number": 3, "periodType": "REG", "maxRegulationPeriods": 3}, "gameOutcome": {"lastPeriodType": "REG"}, "goals": [{"period": 1, "periodDescriptor": {"number": 1, "periodType": "REG", "maxRegulationPeriods": 3}, "timeInPeriod": "04:29", "playerId": 8482145, "name": {"default": "M. Bourque"}, "firstName": {"default": "Mavrik"}, "lastName": {"default": "Bourque"}, "goalModifier": "none", "assists": [{"playerId": 8481581, "name": {"default": "T. Harley"}, "assistsToDate": 5}, {"playerId": 8476889, "name": {"default": "R. Faksa"}, "assistsToDate": 1}], "mugshot": "https://assets.nhle.com/mugs/nhl/20252026/DAL/8482145.png", "teamAbbrev": "DAL", "goalsToDate": 1, "awayScore": 0, "homeScore": 1, "strength": "ev", "highlightClipSharingUrl": "https://nhl.com/video/van-dal-bourque-scores-goal-against-thatcher-demko-6382868930112", "highlightClipSharingUrlFr": "https://nhl.com/fr/video/van-dal-bourque-marque-un-but-contre-thatcher-demko-6382867366112", "highlightClip": 6382868930112, "highlightClipFr": 6382867366112, "discreteClip": 6382866392112, "discreteClipFr": 6382868351112}, {"period": 1, "periodDescriptor": {"number": 1, "periodType": "REG", "maxRegulationPeriods": 3}, "timeInPeriod": "19:22", "playerId": 8478420, "name": {"default": "M. Rantanen"}, "firstName": {"default": "Mikko"}, "lastName": {"default": "Rantanen"}, "goalModifier": "none", "assists": [{"playerId": 8480027, "name": {"default": "J. Robertson"}, "assistsToDate": 3}, {"playerId": 8478449, "name": {"default": "R. Hintz"}, "assistsToDate": 5}], "mugshot": "https://assets.nhle.com/mugs/nhl/20252026/DAL/8478420.png", "teamAbbrev": "DAL", "goalsToDate": 2, "awayScore": 0, "homeScore": 2, "strength": "pp", "highlightClipSharingUrl": "https://nhl.com/video/van-dal-rantanen-scores-ppg-against-thatcher-demko-6382868668112", "highlightClipSharingUrlFr": "https://nhl.com/fr/video/van-dal-rantanen-marque-un-but-en-a-n-contre-thatcher-demko-6382868170112", "highlightClip": 6382868668112, "highlightClipFr": 6382868170112, "discreteClip": 6382868665112, "discreteClipFr": 6382867385112}, {"period": 2, "periodDescriptor": {"number": 2, "periodType": "REG", "maxRegulationPeriods": 3}, "timeInPeriod": "06:40", "playerId": 8480078, "name": {"default": "F. Chytil"}, "firstName": {"default": "Filip"}, "lastName": {"default": "Chytil"}, "goalModifier": "none", "assists": [{"playerId": 8475169, "name": {"default": "E. Kane"}, "assistsToDate": 2}, {"playerId": 8479425, "name": {"default": "F. Hronek"}, "assistsToDate": 1}], "mugshot": "https://assets.nhle.com/mugs/nhl/20252026/VAN/8480078.png", "teamAbbrev": "VAN", "goalsToDate": 3, "awayScore": 1, "homeScore": 2, "strength": "ev", "highlightClipSharingUrl": "https://nhl.com/video/van-dal-chytil-scores-goal-against-casey-desmith-6382868610112", "highlightClipSharingUrlFr": "https://nhl.com/fr/video/van-dal-chytil-marque-un-but-contre-casey-desmith-6382870545112", "highlightClip": 6382868610112, "highlightClipFr": 6382870545112, "discreteClip": 6382868607112, "discreteClipFr": 6382868985112}, {"period": 2, "periodDescriptor": {"number": 2, "periodType": "REG", "maxRegulationPeriods": 3}, "timeInPeriod": "08:50", "playerId": 8478444, "name": {"default": "B. Boeser"}, "firstName": {"default": "Brock"}, "lastName": {"default": "Boeser"}, "goalModifier": "none", "assists": [{"playerId": 8480800, "name": {"default": "Q. Hughes"}, "assistsToDate": 2}, {"playerId": 8480012, "name": {"default": "E. Pettersson"}, "assistsToDate": 2}], "mugshot": "https://assets.nhle.com/mugs/nhl/20252026/VAN/8478444.png", "teamAbbrev": "VAN", "goalsToDate": 3, "awayScore": 2, "homeScore": 2, "strength": "pp", "highlightClipSharingUrl": "https://nhl.com/video/van-dal-boeser-scores-ppg-against-casey-desmith-6382871046112", "highlightClipSharingUrlFr": "https://nhl.com/fr/video/van-dal-boeser-marque-un-but-en-a-n-contre-casey-desmith-6382870158112", "highlightClip": 6382871046112, "highlightClipFr": 6382870158112, "discreteClip": 6382868001112, "discreteClipFr": 6382868995112}, {"period": 2, "periodDescriptor": {"number": 2, "periodType": "REG", "maxRegulationPeriods": 3}, "timeInPeriod": "10:06", "playerId": 8484136, "name": {"default": "M. Sasson"}, "firstName": {"default": "Max"}, "lastName": {"default": "Sasson"}, "goalModifier": "none", "assists": [{"playerId": 8474574, "name": {"default": "T. Myers"}, "assistsToDate": 1}], "mugshot": "https://assets.nhle.com/mugs/nhl/20252026/VAN/8484136.png", "teamAbbrev": "VAN", "goalsToDate": 1, "awayScore": 3, "homeScore": 2, "strength": "ev", "highlightClipSharingUrl": "https://nhl.com/video/van-dal-sasson-scores-goal-against-casey-desmith-6382868909112", "highlightClipSharingUrlFr": "https://nhl.com/fr/video/van-dal-sasson-marque-un-but-contre-casey-desmith-6382870952112", "highlightClip": 6382868909112, "highlightClipFr": 6382870952112, "discreteClip": 6382868005112, "discreteClipFr": 6382870250112}, {"period": 2, "periodDescriptor": {"number": 2, "periodType": "REG", "maxRegulationPeriods": 3}, "timeInPeriod": "18:54", "playerId": 8478856, "name": {"default": "C. Garland"}, "firstName": {"default": "Conor"}, "lastName": {"default": "Garland"}, "goalModifier": "none", "assists": [], "mugshot": "https://assets.nhle.com/mugs/nhl/20252026/VAN/8478856.png", "teamAbbrev": "VAN", "goalsToDate": 1, "awayScore": 4, "homeScore": 2, "strength": "ev", "highlightClipSharingUrl": "https://nhl.com/video/van-dal-garland-scores-goal-against-casey-desmith-6382871175112", "highlightClipSharingUrlFr": "https://nhl.com/fr/video/van-dal-garland-marque-un-but-contre-casey-desmith-6382871176112", "highlightClip": 6382871175112, "highlightClipFr": 6382871176112, "discreteClip": 6382870274112, "discreteClipFr": 6382870381112}, {"period": 3, "periodDescriptor": {"number": 3, "periodType": "REG", "maxRegulationPeriods": 3}, "timeInPeriod": "17:52", "playerId": 8482740, "name": {"default": "W. Johnston"}, "firstName": {"default": "Wyatt"}, "lastName": {"default": "Johnston"}, "goalModifier": "none", "assists": [{"playerId": 8475794, "name": {"default": "T. Seguin"}, "assistsToDate": 2}, {"playerId": 8480027, "name": {"default": "J. Robertson"}, "assistsToDate": 4}], "mugshot": "https://assets.nhle.com/mugs/nhl/20252026/DAL/8482740.png", "teamAbbrev": "DAL", "goalsToDate": 4, "awayScore": 4, "homeScore": 3, "strength": "pp", "highlightClipSharingUrl": "https://nhl.com/video/van-dal-johnston-scores-ppg-against-thatcher-demko-6382871228112", "highlightClipSharingUrlFr": "https://nhl.com/fr/video/van-dal-johnston-marque-un-but-en-a-n-contre-thatcher-demko-6382870830112", "highlightClip": 6382871228112, "highlightClipFr": 6382870830112, "discreteClip": 6382870431112, "discreteClipFr": 6382872778112}, {"period": 3, "periodDescriptor": {"number": 3, "periodType": "REG", "maxRegulationPeriods": 3}, "timeInPeriod": "19:23", "playerId": 8480800, "name": {"default": "Q. Hughes"}, "firstName": {"default": "Quinn"}, "lastName": {"default": "Hughes"}, "goalModifier": "none", "assists": [{"playerId": 8478856, "name": {"default": "C. Garland"}, "assistsToDate": 2}, {"playerId": 8479425, "name": {"default": "F. Hronek"}, "assistsToDate": 2}], "mugshot": "https://assets.nhle.com/mugs/nhl/20252026/VAN/8480800.png", "teamAbbrev": "VAN", "goalsToDate": 1, "awayScore": 5, "homeScore": 3, "strength": "pp", "highlightClipSharingUrl": "https://nhl.com/video/van-dal-hughes-scores-goal-against-casey-desmith-6382872114112", "highlightClipSharingUrlFr": "https://nhl.com/fr/video/van-dal-hughes-marque-un-but-contre-casey-desmith-6382871618112", "highlightClip": 6382872114112, "highlightClipFr": 6382871618112, "discreteClip": 6382871032112, "discreteClipFr": 6382871217112}]}, {"id": 2025020069, "season": 20252026, "gameType": 2, "gameDate": "2025-10-16", "venue": {"default": "T-Mobile Arena"}, "startTimeUTC": "2025-10-17T02:00:00Z", "easternUTCOffset": "-04:00", "venueUTCOffset": "-07:00", "tvBroadcasts": [{"id": 31, "market": "A", "countryCode": "US", "network": "NESN", "sequenceNumber": 405}, {"id": 521, "market": "H", "countryCode": "US", "network": "SCRIPPS", "sequenceNumber": 657}], "gameState": "OFF", "gameScheduleState": "OK", "awayTeam": {"id": 6, "name": {"default": "Bruins"}, "abbrev": "BOS", "score": 5, "sog": 24, "logo": "https://assets.nhle.com/logos/nhl/svg/BOS_light.svg?season=20252026"}, "homeTeam": {"id": 54, "name": {"default": "Golden Knights"}, "abbrev": "VGK", "score": 6, "sog": 37, "logo": "https://assets.nhle.com/logos/nhl/svg/VGK_light.svg"}, "gameCenterLink": "/gamecenter/bos-vs-vgk/2025/10/16/2025020069", "threeMinRecap": "/video/bos-at-vgk-recap-6382875923112", "threeMinRecapFr": "/fr/video/bos-vs-vgk-16-10-2025-resume-6382874459112", "condensedGame": "/video/bos-at-vgk-condensed-game-6382876416112", "condensedGameFr": "/fr/video/match-condense-bruins-golden-knights-16-10-2025-6382875044112", "clock": {"timeRemaining": "00:00", "secondsRemaining": 0, "running": false, "inIntermission": false}, "neutralSite": false, "venueTimezone": "US/Pacific", "period": 3, "periodDescriptor": {"number": 3, "periodType": "REG", "maxRegulationPeriods": 3}, "gameOutcome": {"lastPeriodType": "REG"}, "goals": [{"period": 1, "periodDescriptor": {"number": 1, "periodType": "REG", "maxRegulationPeriods": 3}, "timeInPeriod": "02:05", "playerId": 8479661, "name": {"default": "T. Jeannot"}, "firstName": {"default": "Tanner"}, "lastName": {"default": "Jeannot"}, "goalModifier": "none", "assists": [{"playerId": 8479325, "name": {"default": "C. McAvoy"}, "assistsToDate": 2}, {"playerId": 8479591, "name": {"default": "M. Eyssimont"}, "assistsToDate": 2}], "mugshot": "https://assets.nhle.com/mugs/nhl/20252026/BOS/8479661.png", "teamAbbrev": "BOS", "goalsToDate": 2, "awayScore": 1, "homeScore": 0, "strength": "ev", "highlightClipSharingUrl": "https://nhl.com/video/bos-vgk-jeannot-scores-goal-against-akira-schmid-6382871903112", "highlightClipSharingUrlFr": "https://nhl.com/fr/video/bos-vgk-jeannot-marque-un-but-contre-akira-schmid-6382872769112", "highlightClip": 6382871903112, "highlightClipFr": 6382872769112, "discreteClip": 6382871107112, "discreteClipFr": 6382871302112}, {"period": 1, "periodDescriptor": {"number": 1, "periodType": "REG", "maxRegulationPeriods": 3}, "timeInPeriod": "03:35", "playerId": 8481604, "name": {"default": "P. Dorofeyev", "cs": "P. Dorofejev", "fi": "P. Dorofejev", "sk": "P. Dorofejev"}, "firstName": {"default": "Pavel"}, "lastName": {"default": "Dorofeyev", "cs": "Dorofejev", "fi": "Dorofejev", "sk": "Dorofejev"}, "goalModifier": "none", "assists": [{"playerId": 8478483, "name": {"default": "M. Marner"}, "assistsToDate": 5}, {"playerId": 8480727, "name": {"default": "Z. Whitecloud"}, "assistsToDate": 1}], "mugshot": "https://assets.nhle.com/mugs/nhl/20252026/VGK/8481604.png", "teamAbbrev": "VGK", "goalsToDate": 6, "awayScore": 1, "homeScore": 1, "strength": "ev", "highlightClipSharingUrl": "https://nhl.com/video/bos-vgk-dorofeyev-scores-goal-against-jeremy-swayman-6382872103112", "highlightClipSharingUrlFr": "https://nhl.com/fr/video/bos-vgk-dorofeyev-marque-un-but-contre-jeremy-swayman-6382870319112", "highlightClip": 6382872103112, "highlightClipFr": 6382870319112, "discreteClip": 6382871814112, "discreteClipFr": 6382872475112}, {"period": 1, "periodDescriptor": {"number": 1, "periodType": "REG", "maxRegulationPeriods": 3}, "timeInPeriod": "16:44", "playerId": 8477507, "name": {"default": "N. Zadorov"}, "firstName": {"default": "Nikita"}, "lastName": {"default": "Zadorov"}, "goalModifier": "none", "assists": [{"playerId": 8480035, "name": {"default": "H. Jokiharju"}, "assistsToDate": 2}, {"playerId": 8476374, "name": {"default": "S. Kuraly"}, "assistsToDate": 1}], "mugshot": "https://assets.nhle.com/mugs/nhl/20252026/BOS/8477507.png", "teamAbbrev": "BOS", "goalsToDate": 1, "awayScore": 2, "homeScore": 1, "strength": "ev", "highlightClipSharingUrl": "https://nhl.com/video/bos-vgk-zadorov-scores-goal-against-akira-schmid-6382872013112", "highlightClipSharingUrlFr": "https://nhl.com/fr/video/bos-vgk-zadorov-marque-un-but-contre-akira-schmid-6382871713112", "highlightClip": 6382872013112, "highlightClipFr": 6382871713112, "discreteClip": 6382872012112, "discreteClipFr": 6382873374112}, {"period": 1, "periodDescriptor": {"number": 1, "periodType": "REG", "maxRegulationPeriods": 3}, "timeInPeriod": "18:33", "playerId": 8481133, "name": {"default": "C. Reinhardt"}, "firstName": {"default": "Cole"}, "lastName": {"default": "Reinhardt"}, "goalModifier": "none", "assists": [{"playerId": 8477018, "name": {"default": "B. Hutton"}, "assistsToDate": 2}, {"playerId": 8476925, "name": {"default": "C. Sissons"}, "assistsToDate": 1}], "mugshot": "https://assets.nhle.com/mugs/nhl/20252026/VGK/8481133.png", "teamAbbrev": "VGK", "goalsToDate": 1, "awayScore": 2, "homeScore": 2, "strength": "ev", "highlightClipSharingUrl": "https://nhl.com/video/bos-vgk-reinhardt-scores-goal-against-jeremy-swayman-6382871424112", "highlightClipSharingUrlFr": "https://nhl.com/fr/video/bos-vgk-reinhardt-marque-un-but-contre-jeremy-swayman-6382870839112", "highlightClip": 6382871424112, "highlightClipFr": 6382870839112, "discreteClip": 6382873670112, "discreteClipFr": 6382871233112}, {"period": 2, "periodDescriptor": {"number": 2, "periodType": "REG", "maxRegulationPeriods": 3}, "timeInPeriod": "04:14", "playerId": 8478403, "name": {"default": "J. Eichel"}, "firstName": {"default": "Jack"}, "lastName": {"default": "Eichel"}, "goalModifier": "none", "assists": [{"playerId": 8475913, "name": {"default": "M. Stone"}, "assistsToDate": 7}, {"playerId": 8477964, "name": {"default": "I. Barbashev", "cs": "I. Barba\u0161ev", "fi": "I. Barbashov", "sk": "I. Barba\u0161ev"}, "assistsToDate": 3}], "mugshot": "https://assets.nhle.com/mugs/nhl/20252026/VGK/8478403.png", "teamAbbrev": "VGK", "goalsToDate": 5, "awayScore": 2, "homeScore": 3, "strength": "ev", "highlightClipSharingUrl": "https://nhl.com/video/bos-vgk-eichel-scores-goal-against-jeremy-swayman-6382872815112", "highlightClipSharingUrlFr": "https://nhl.com/fr/video/bos-vgk-eichel-marque-un-but-contre-jeremy-swayman-6382871947112", "highlightClip": 6382872815112, "highlightClipFr": 6382871947112, "discreteClip": 6382873991112, "discreteClipFr": 6382871739112}, {"period": 2, "periodDescriptor": {"number": 2, "periodType": "REG", "maxRegulationPeriods": 3}, "timeInPeriod": "06:35", "playerId": 8476881, "name": {"default": "T. Hertl"}, "firstName": {"default": "Tomas", "cs": "Tom\u00e1\u0161", "sk": "Tom\u00e1\u0161"}, "lastName": {"default": "Hertl"}, "goalModifier": "none", "assists": [{"playerId": 8481604, "name": {"default": "P. Dorofeyev", "cs": "P. Dorofejev", "fi": "P. Dorofejev", "sk": "P. Dorofejev"}, "assistsToDate": 1}, {"playerId": 8475913, "name": {"default": "M. Stone"}, "assistsToDate": 8}], "mugshot": "https://assets.nhle.com/mugs/nhl/20252026/VGK/8476881.png", "teamAbbrev": "VGK", "goalsToDate": 2, "awayScore": 2, "homeScore": 4, "strength": "pp", "highlightClipSharingUrl": "https://nhl.com/video/bos-vgk-hertl-scores-ppg-against-jeremy-swayman-6382874582112", "highlightClipSharingUrlFr": "https://nhl.com/fr/video/bos-vgk-hertl-marque-un-but-en-a-n-contre-jeremy-swayman-6382872909112", "highlightClip": 6382874582112, "highlightClipFr": 6382872909112, "discreteClip": 6382873217112, "discreteClipFr": 6382872719112}, {"period": 2, "periodDescriptor": {"number": 2, "periodType": "REG", "maxRegulationPeriods": 3}, "timeInPeriod": "08:15", "playerId": 8477956, "name": {"default": "D. Pastrnak", "cs": "D. Pastr\u0148\u00e1k", "sk": "D. Pastr\u0148\u00e1k"}, "firstName": {"default": "David"}, "lastName": {"default": "Pastrnak", "cs": "Pastr\u0148\u00e1k", "sk": "Pastr\u0148\u00e1k"}, "goalModifier": "none", "assists": [{"playerId": 8479987, "name": {"default": "M. Geekie"}, "assistsToDate": 2}, {"playerId": 8477496, "name": {"default": "E. Lindholm"}, "assistsToDate": 3}], "mugshot": "https://assets.nhle.com/mugs/nhl/20252026/BOS/8477956.png", "teamAbbrev": "BOS", "goalsToDate": 2, "awayScore": 3, "homeScore": 4, "strength": "pp", "highlightClipSharingUrl": "https://nhl.com/video/bos-vgk-pastrnak-scores-ppg-against-akira-schmid-6382873407112", "highlightClipSharingUrlFr": "https://nhl.com/fr/video/bos-vgk-pastrnak-marque-un-but-en-a-n-contre-akira-schmid-6382873804112", "highlightClip": 6382873407112, "highlightClipFr": 6382873804112, "discreteClip": 6382874587112, "discreteClipFr": 6382873311112}, {"period": 2, "periodDescriptor": {"number": 2, "periodType": "REG", "maxRegulationPeriods": 3}, "timeInPeriod": "18:24", "playerId": 8476448, "name": {"default": "W. Karlsson"}, "firstName": {"default": "William"}, "lastName": {"default": "Karlsson"}, "goalModifier": "none", "assists": [{"playerId": 8475913, "name": {"default": "M. Stone"}, "assistsToDate": 9}], "mugshot": "https://assets.nhle.com/mugs/nhl/20252026/VGK/8476448.png", "teamAbbrev": "VGK", "goalsToDate": 1, "awayScore": 3, "homeScore": 5, "strength": "sh", "highlightClipSharingUrl": "https://nhl.com/video/bos-vgk-karlsson-scores-shg-against-jeremy-swayman-6382873634112", "highlightClipSharingUrlFr": "https://nhl.com/fr/video/bos-vgk-karlsson-marque-un-but-en-i-n-contre-jeremy-swayman-6382873046112", "highlightClip": 6382873634112, "highlightClipFr": 6382873046112, "discreteClip": 6382872938112, "discreteClipFr": 6382873426112}, {"period": 3, "periodDescriptor": {"number": 3, "periodType": "REG", "maxRegulationPeriods": 3}, "timeInPeriod": "02:19", "playerId": 8476448, "name": {"default": "W. Karlsson"}, "firstName": {"default": "William"}, "lastName": {"default": "Karlsson"}, "goalModifier": "none", "assists": [{"playerId": 8478483, "name": {"default": "M. Marner"}, "assistsToDate": 6}, {"playerId": 8478403, "name": {"default": "J. Eichel"}, "assistsToDate": 6}], "mugshot": "https://assets.nhle.com/mugs/nhl/20252026/VGK/8476448.png", "teamAbbrev": "VGK", "goalsToDate": 2, "awayScore": 3, "homeScore": 6, "strength": "pp", "highlightClipSharingUrl": "https://nhl.com/video/bos-vgk-karlsson-scores-ppg-against-jeremy-swayman-6382874134112", "highlightClipSharingUrlFr": "https://nhl.com/fr/video/bos-vgk-karlsson-marque-un-but-en-a-n-contre-jeremy-swayman-6382873447112", "highlightClip": 6382874134112, "highlightClipFr": 6382873447112, "discreteClip": 6382875692112, "discreteClipFr": 6382874333112}, {"period": 3, "periodDescriptor": {"number": 3, "periodType": "REG", "maxRegulationPeriods": 3}, "timeInPeriod": "04:05", "playerId": 8480355, "name": {"default": "M. Kastelic"}, "firstName": {"default": "Mark"}, "lastName": {"default": "Kastelic"}, "goalModifier": "none", "assists": [{"playerId": 8476374, "name": {"default": "S. Kuraly"}, "assistsToDate": 2}], "mugshot": "https://assets.nhle.com/mugs/nhl/20252026/BOS/8480355.png", "teamAbbrev": "BOS", "goalsToDate": 2, "awayScore": 4, "homeScore": 6, "strength": "ev", "highlightClipSharingUrl": "https://nhl.com/video/bos-vgk-kastelic-scores-goal-against-akira-schmid-6382874618112", "highlightClipSharingUrlFr": "https://nhl.com/fr/video/bos-vgk-kastelic-marque-un-but-contre-akira-schmid-6382874754112", "highlightClip": 6382874618112, "highlightClipFr": 6382874754112, "discreteClip": 6382875231112, "discreteClipFr": 6382873453112}, {"period": 3, "periodDescriptor": {"number": 3, "periodType": "REG", "maxRegulationPeriods": 3}, "timeInPeriod": "05:12", "playerId": 8479591, "name": {"default": "M. Eyssimont"}, "firstName": {"default": "Michael"}, "lastName": {"default": "Eyssimont"}, "goalModifier": "none", "assists": [{"playerId": 8482511, "name": {"default": "M. Lohrei"}, "assistsToDate": 1}], "mugshot": "https://assets.nhle.com/mugs/nhl/20252026/BOS/8479591.png", "teamAbbrev": "BOS", "goalsToDate": 1, "awayScore": 5, "homeScore": 6, "strength": "ev", "highlightClipSharingUrl": "https://nhl.com/video/bos-vgk-eyssimont-scores-goal-against-akira-schmid-6382873848112", "highlightClipSharingUrlFr": "https://nhl.com/fr/video/bos-vgk-eyssimont-marque-un-but-contre-akira-schmid-6382875020112", "highlightClip": 6382873848112, "highlightClipFr": 6382875020112, "discreteClip": 6382875504112, "discreteClipFr": 6382875019112}]}, {"id": 2025020070, "season": 20252026, "gameType": 2, "gameDate": "2025-10-16", "venue": {"default": "Honda Center"}, "startTimeUTC": "2025-10-17T02:00:00Z", "easternUTCOffset": "-04:00", "venueUTCOffset": "-07:00", "tvBroadcasts": [{"id": 561, "market": "A", "countryCode": "US", "network": "FDSNSO", "sequenceNumber": 202}, {"id": 553, "market": "H", "countryCode": "US", "network": "Victory+", "sequenceNumber": 382}, {"id": 219, "market": "H", "countryCode": "US", "network": "KCOP-13", "sequenceNumber": 656}], "gameState": "OFF", "gameScheduleState": "OK", "awayTeam": {"id": 12, "name": {"default": "Hurricanes"}, "abbrev": "CAR", "score": 4, "sog": 32, "logo": "https://assets.nhle.com/logos/nhl/svg/CAR_light.svg"}, "homeTeam": {"id": 24, "name": {"default": "Ducks"}, "abbrev": "ANA", "score": 1, "sog": 24, "logo": "https://assets.nhle.com/logos/nhl/svg/ANA_light.svg"}, "gameCenterLink": "/gamecenter/car-vs-ana/2025/10/16/2025020070", "threeMinRecap": "/video/car-at-ana-recap-6382876499112", "clock": {"timeRemaining": "00:00", "secondsRemaining": 0, "running": false, "inIntermission": false}, "neutralSite": false, "venueTimezone": "America/Los_Angeles", "period": 3, "periodDescriptor": {"number": 3, "periodType": "REG", "maxRegulationPeriods": 3}, "gameOutcome": {"lastPeriodType": "REG"}, "goals": [{"period": 1, "periodDescriptor": {"number": 1, "periodType": "REG", "maxRegulationPeriods": 3}, "timeInPeriod": "14:54", "playerId": 8482093, "name": {"default": "S. Jarvis"}, "firstName": {"default": "Seth"}, "lastName": {"default": "Jarvis"}, "goalModifier": "none", "assists": [{"playerId": 8476906, "name": {"default": "S. Gostisbehere"}, "assistsToDate": 4}], "mugshot": "https://assets.nhle.com/mugs/nhl/20252026/CAR/8482093.png", "teamAbbrev": "CAR", "goalsToDate": 4, "awayScore": 1, "homeScore": 0, "strength": "ev", "highlightClipSharingUrl": "https://nhl.com/video/car-ana-jarvis-scores-goal-against-lukas-dostal-6382872383112", "highlightClipSharingUrlFr": "https://nhl.com/fr/video/car-ana-jarvis-marque-un-but-contre-lukas-dostal-6382870629112", "highlightClip": 6382872383112, "highlightClipFr": 6382870629112, "discreteClip": 6382870732112, "discreteClipFr": 6382871524112}, {"period": 2, "periodDescriptor": {"number": 2, "periodType": "REG", "maxRegulationPeriods": 3}, "timeInPeriod": "10:22", "playerId": 8482093, "name": {"default": "S. Jarvis"}, "firstName": {"default": "Seth"}, "lastName": {"default": "Jarvis"}, "goalModifier": "none", "assists": [{"playerId": 8482809, "name": {"default": "J. Blake"}, "assistsToDate": 3}, {"playerId": 8476906, "name": {"default": "S. Gostisbehere"}, "assistsToDate": 5}], "mugshot": "https://assets.nhle.com/mugs/nhl/20252026/CAR/8482093.png", "teamAbbrev": "CAR", "goalsToDate": 5, "awayScore": 2, "homeScore": 0, "strength": "pp", "highlightClipSharingUrl": "https://nhl.com/video/car-ana-jarvis-scores-ppg-against-lukas-dostal-6382872152112", "highlightClipSharingUrlFr": "https://nhl.com/fr/video/car-ana-jarvis-marque-un-but-en-a-n-contre-lukas-dostal-6382873789112", "highlightClip": 6382872152112, "highlightClipFr": 6382873789112, "discreteClip": 6382872816112, "discreteClipFr": 6382872150112}, {"period": 2, "periodDescriptor": {"number": 2, "periodType": "REG", "maxRegulationPeriods": 3}, "timeInPeriod": "11:32", "playerId": 8484153, "name": {"default": "L. Carlsson"}, "firstName": {"default": "Leo"}, "lastName": {"default": "Carlsson"}, "goalModifier": "none", "assists": [{"playerId": 8473986, "name": {"default": "A. Killorn"}, "assistsToDate": 1}, {"playerId": 8481563, "name": {"default": "D. Helleson"}, "assistsToDate": 1}], "mugshot": "https://assets.nhle.com/mugs/nhl/20252026/ANA/8484153.png", "teamAbbrev": "ANA", "goalsToDate": 2, "awayScore": 2, "homeScore": 1, "strength": "ev", "highlightClipSharingUrl": "https://nhl.com/video/car-ana-carlsson-scores-goal-against-frederik-andersen-6382873403112", "highlightClipSharingUrlFr": "https://nhl.com/fr/video/car-ana-carlsson-marque-un-but-contre-frederik-andersen-6382873794112", "highlightClip": 6382873403112, "highlightClipFr": 6382873794112, "discreteClip": 6382873402112, "discreteClipFr": 6382873791112}, {"period": 3, "periodDescriptor": {"number": 3, "periodType": "REG", "maxRegulationPeriods": 3}, "timeInPeriod": "02:38", "playerId": 8482100, "name": {"default": "A. Nikishin"}, "firstName": {"default": "Alexander"}, "lastName": {"default": "Nikishin"}, "goalModifier": "none", "assists": [{"playerId": 8478427, "name": {"default": "S. Aho"}, "assistsToDate": 5}, {"playerId": 8476906, "name": {"default": "S. Gostisbehere"}, "assistsToDate": 6}], "mugshot": "https://assets.nhle.com/mugs/nhl/20252026/CAR/8482100.png", "teamAbbrev": "CAR", "goalsToDate": 1, "awayScore": 3, "homeScore": 1, "strength": "ev", "highlightClipSharingUrl": "https://nhl.com/video/car-ana-nikishin-scores-goal-against-lukas-dostal-6382873946112", "highlightClipSharingUrlFr": "https://nhl.com/fr/video/car-ana-nikishin-marque-un-but-contre-lukas-dostal-6382875493112", "highlightClip": 6382873946112, "highlightClipFr": 6382875493112, "discreteClip": 6382873255112, "discreteClipFr": 6382873538112}, {"period": 3, "periodDescriptor": {"number": 3, "periodType": "REG", "maxRegulationPeriods": 3}, "timeInPeriod": "15:48", "playerId": 8478427, "name": {"default": "S. Aho"}, "firstName": {"default": "Sebastian"}, "lastName": {"default": "Aho"}, "goalModifier": "none", "assists": [{"playerId": 8482093, "name": {"default": "S. Jarvis"}, "assistsToDate": 2}], "mugshot": "https://assets.nhle.com/mugs/nhl/20252026/CAR/8478427.png", "teamAbbrev": "CAR", "goalsToDate": 1, "awayScore": 4, "homeScore": 1, "strength": "ev", "highlightClipSharingUrl": "https://nhl.com/video/car-ana-aho-scores-goal-against-lukas-dostal-6382876000112", "highlightClipSharingUrlFr": "https://nhl.com/fr/video/car-ana-aho-marque-un-but-contre-lukas-dostal-6382875906112", "highlightClip": 6382876000112, "highlightClipFr": 6382875906112, "discreteClip": 6382874946112, "discreteClipFr": 6382874763112}]}, {"id": 2025020071, "season": 20252026, "gameType": 2, "gameDate": "2025-10-16", "venue": {"default": "Crypto.com Arena"}, "startTimeUTC": "2025-10-17T02:00:00Z", "easternUTCOffset": "-04:00", "venueUTCOffset": "-07:00", "tvBroadcasts": [{"id": 564, "market": "H", "countryCode": "US", "network": "FDSNW", "sequenceNumber": 288}, {"id": 528, "market": "A", "countryCode": "US", "network": "SN-PIT", "sequenceNumber": 384}], "gameState": "OFF", "gameScheduleState": "OK", "awayTeam": {"id": 5, "name": {"default": "Penguins"}, "abbrev": "PIT", "score": 4, "sog": 26, "logo": "https://assets.nhle.com/logos/nhl/svg/PIT_light.svg"}, "homeTeam": {"id": 26, "name": {"default": "Kings"}, "abbrev": "LAK", "score": 2, "sog": 32, "logo": "https://assets.nhle.com/logos/nhl/svg/LAK_light.svg"}, "gameCenterLink": "/gamecenter/pit-vs-lak/2025/10/16/2025020071", "threeMinRecap": "/video/pit-at-lak-recap-6382874770112", "threeMinRecapFr": "/fr/video/pit-vs-lak-16-10-2025-resume-6382875440112", "condensedGame": "/video/pit-at-lak-condensed-game-6382874638112", "condensedGameFr": "/fr/video/match-condense-penguins-kings-16-10-2025-6382873158112", "clock": {"timeRemaining": "00:00", "secondsRemaining": 0, "running": false, "inIntermission": false}, "neutralSite": false, "venueTimezone": "America/Los_Angeles", "period": 3, "periodDescriptor": {"number": 3, "periodType": "REG", "maxRegulationPeriods": 3}, "gameOutcome": {"lastPeriodType": "REG"}, "goals": [{"period": 1, "periodDescriptor": {"number": 1, "periodType": "REG", "maxRegulationPeriods": 3}, "timeInPeriod": "04:24", "playerId": 8477998, "name": {"default": "W. Foegele"}, "firstName": {"default": "Warren"}, "lastName": {"default": "Foegele"}, "goalModifier": "none", "assists": [{"playerId": 8479675, "name": {"default": "T. Moore"}, "assistsToDate": 1}, {"playerId": 8476879, "name": {"default": "C. Ceci"}, "assistsToDate": 1}], "mugshot": "https://assets.nhle.com/mugs/nhl/20252026/LAK/8477998.png", "teamAbbrev": "LAK", "goalsToDate": 1, "awayScore": 0, "homeScore": 1, "strength": "ev", "highlightClipSharingUrl": "https://nhl.com/video/pit-lak-foegele-scores-goal-against-arturs-silovs-6382870611112", "highlightClipSharingUrlFr": "https://nhl.com/fr/video/pit-lak-foegele-marque-un-but-contre-arturs-silovs-6382870907112", "highlightClip": 6382870611112, "highlightClipFr": 6382870907112, "discreteClip": 6382872169112, "discreteClipFr": 6382871801112}, {"period": 1, "periodDescriptor": {"number": 1, "periodType": "REG", "maxRegulationPeriods": 3}, "timeInPeriod": "09:04", "playerId": 8477942, "name": {"default": "K. Fiala"}, "firstName": {"default": "Kevin"}, "lastName": {"default": "Fiala"}, "goalModifier": "none", "assists": [{"playerId": 8482124, "name": {"default": "Q. Byfield"}, "assistsToDate": 3}, {"playerId": 8476469, "name": {"default": "J. Armia"}, "assistsToDate": 3}], "mugshot": "https://assets.nhle.com/mugs/nhl/20252026/LAK/8477942.png", "teamAbbrev": "LAK", "goalsToDate": 3, "awayScore": 0, "homeScore": 2, "strength": "ev", "highlightClipSharingUrl": "https://nhl.com/video/pit-lak-fiala-scores-goal-against-arturs-silovs-6382871803112", "highlightClipSharingUrlFr": "https://nhl.com/fr/video/pit-lak-fiala-marque-un-but-contre-arturs-silovs-6382872558112", "highlightClip": 6382871803112, "highlightClipFr": 6382872558112, "discreteClip": 6382871016112, "discreteClipFr": 6382869818112}, {"period": 2, "periodDescriptor": {"number": 2, "periodType": "REG", "maxRegulationPeriods": 3}, "timeInPeriod": "06:37", "playerId": 8471215, "name": {"default": "E. Malkin"}, "firstName": {"default": "Evgeni", "cs": "Jevgenij", "fi": "Jevgeni", "sk": "Jevgenij"}, "lastName": {"default": "Malkin"}, "goalModifier": "none", "assists": [{"playerId": 8475810, "name": {"default": "B. Rust"}, "assistsToDate": 2}, {"playerId": 8474578, "name": {"default": "E. Karlsson"}, "assistsToDate": 1}], "mugshot": "https://assets.nhle.com/mugs/nhl/20252026/PIT/8471215.png", "teamAbbrev": "PIT", "goalsToDate": 1, "awayScore": 1, "homeScore": 2, "strength": "pp", "highlightClipSharingUrl": "https://nhl.com/video/pit-lak-malkin-scores-ppg-against-anton-forsberg-6382871735112", "highlightClipSharingUrlFr": "https://nhl.com/fr/video/pit-lak-malkin-marque-un-but-en-a-n-contre-anton-forsberg-6382872146112", "highlightClip": 6382871735112, "highlightClipFr": 6382872146112, "discreteClip": 6382872901112, "discreteClipFr": 6382873301112}, {"period": 2, "periodDescriptor": {"number": 2, "periodType": "REG", "maxRegulationPeriods": 3}, "timeInPeriod": "07:18", "playerId": 8480980, "name": {"default": "C. Dewar"}, "firstName": {"default": "Connor"}, "lastName": {"default": "Dewar"}, "goalModifier": "none", "assists": [{"playerId": 8478569, "name": {"default": "N. Acciari"}, "assistsToDate": 1}, {"playerId": 8478854, "name": {"default": "R. Shea"}, "assistsToDate": 4}], "mugshot": "https://assets.nhle.com/mugs/nhl/20252026/PIT/8480980.png", "teamAbbrev": "PIT", "goalsToDate": 1, "awayScore": 2, "homeScore": 2, "strength": "ev", "highlightClipSharingUrl": "https://nhl.com/video/pit-lak-dewar-scores-goal-against-anton-forsberg-6382872521112", "highlightClipSharingUrlFr": "https://nhl.com/fr/video/pit-lak-dewar-marque-un-but-contre-anton-forsberg-6382871939112", "highlightClip": 6382872521112, "highlightClipFr": 6382871939112, "discreteClip": 6382873006112, "discreteClipFr": 6382874077112}, {"period": 3, "periodDescriptor": {"number": 3, "periodType": "REG", "maxRegulationPeriods": 3}, "timeInPeriod": "06:50", "playerId": 8480842, "name": {"default": "F. Hallander"}, "firstName": {"default": "Filip"}, "lastName": {"default": "Hallander"}, "goalModifier": "none", "assists": [{"playerId": 8476483, "name": {"default": "R. Rakell"}, "assistsToDate": 2}, {"playerId": 8478450, "name": {"default": "P. Wotherspoon"}, "assistsToDate": 1}], "mugshot": "https://assets.nhle.com/mugs/nhl/20252026/PIT/8480842.png", "teamAbbrev": "PIT", "goalsToDate": 1, "awayScore": 3, "homeScore": 2, "strength": "sh", "highlightClipSharingUrl": "https://nhl.com/video/pit-lak-hallander-scores-shg-against-anton-forsberg-6382875306112", "highlightClipSharingUrlFr": "https://nhl.com/fr/video/pit-lak-hallander-marque-un-but-en-i-n-contre-anton-forsberg-6382873335112", "highlightClip": 6382875306112, "highlightClipFr": 6382873335112, "discreteClip": 6382873332112, "discreteClipFr": 6382873247112}, {"period": 3, "periodDescriptor": {"number": 3, "periodType": "REG", "maxRegulationPeriods": 3}, "timeInPeriod": "19:29", "playerId": 8471675, "name": {"default": "S. Crosby"}, "firstName": {"default": "Sidney"}, "lastName": {"default": "Crosby"}, "goalModifier": "empty-net", "assists": [{"playerId": 8478450, "name": {"default": "P. Wotherspoon"}, "assistsToDate": 2}, {"playerId": 8474578, "name": {"default": "E. Karlsson"}, "assistsToDate": 2}], "mugshot": "https://assets.nhle.com/mugs/nhl/20252026/PIT/8471675.png", "teamAbbrev": "PIT", "goalsToDate": 2, "awayScore": 4, "homeScore": 2, "strength": "ev", "highlightClipSharingUrl": "https://nhl.com/video/pit-lak-crosby-scores-empty-net-goal-6382874346112", "highlightClipSharingUrlFr": "https://nhl.com/fr/video/pit-lak-crosby-pit-marque-un-but-dans-un-filet-desert-6382875997112", "highlightClip": 6382874346112, "highlightClipFr": 6382875997112, "discreteClip": 6382875806112, "discreteClipFr": 6382875622112}]}]}}