{"ts": 1774674661.1305194, "data": {"prevDate": "2025-02-08", "currentDate": "2025-02-09", "nextDate": "2025-02-12", "gameWeek": [{"date": "2025-02-06", "dayAbbrev": "THU", "numberOfGames": 9}, {"date": "2025-02-07", "dayAbbrev": "FRI", "numberOfGames": 5}, {"date": "2025-02-08", "dayAbbrev": "SAT", "numberOfGames": 14}, {"date": "2025-02-09", "dayAbbrev": "SUN", "numberOfGames": 2}, {"date": "2025-02-10", "dayAbbrev": "MON", "numberOfGames": 0}, {"date": "2025-02-11", "dayAbbrev": "TUE", "numberOfGames": 0}, {"date": "2025-02-12", "dayAbbrev": "WED", "numberOfGames": 1}], "oddsPartners": [{"partnerId": 2, "country": "SE", "name": "Unibet", "imageUrl": "https://assets.nhle.com/betting_partner/unibet.svg", "siteUrl": "https://www.unibet.se/betting/sports/filter/ice_hockey/nhl/all/matches", "bgColor": "#14805E", "textColor": "#FFFFFF", "accentColor": "#3AAA35"}, {"partnerId": 3, "country": "CZ", "name": "Tipsport", "imageUrl": "https://assets.nhle.com/betting_partner/tipsport.svg", "siteUrl": "https://www.tipsport.cz/PartnerRedirectAction.do?pid=16961&sid=20360&bid=34954&tid=11268", "bgColor": "#2497F2", "textColor": "#FFFFFF", "accentColor": "#FFFFFF"}, {"partnerId": 6, "country": "FI", "name": "Veikkaus", "imageUrl": "https://assets.nhle.com/betting_partner/veikkaus.svg", "siteUrl": "https://www.veikkaus.fi/fi/vedonlyonti/pitkaveto?t=3-2-1_NHL", "bgColor": "#0025F5", "textColor": "#FFFFFF", "accentColor": "#FFFFFF"}, {"partnerId": 7, "country": "CA", "name": "FanDuel", "imageUrl": "https://assets.nhle.com/betting_partner/fanduel.svg", "siteUrl": "https://fanduel.com", "bgColor": "#0078ff", "textColor": "#FFFFFF", "accentColor": "#FFFFFF"}, {"partnerId": 8, "country": "DE", "name": "Sportradar", "imageUrl": "https://assets.nhle.com/betting_partner/sportsradar.svg", "siteUrl": "https://sportradar.com", "bgColor": "#000000", "textColor": "#FFFFFF", "accentColor": "#E6E6E6"}, {"partnerId": 9, "country": "US", "name": "DraftKings", "imageUrl": "https://assets.nhle.com/betting_partner/draftkings.svg", "siteUrl": "https://dksb.sng.link/As9kz/3i4d?_dl=https%3A%2F%2Fsportsbook.draftkings.com%2Fgateway%3Fs%3D333653091&pcid=427326&psn=1320&pcn=NHL&pscn=OddsWidget&pcrn=NoOffer&pscid=SP&wpcid=427326&wpsrc=1320&wpcn=NHL&wpscn=OddsWidget&wpcrn=NoOffer&wpscid=SP&_forward_params=1", "bgColor": "#000000", "textColor": "#FFFFFF", "accentColor": "#FFFFFF"}, {"partnerId": 10, "country": "SK", "name": "Doxxbet", "imageUrl": "https://assets.nhle.com/betting_partner/doxxbet.svg", "siteUrl": "https://www.doxxbet.sk/sk/sportove-tipovanie-online/kurzy/ladovy-hokej/usa/nhl/?msID=21&mbID=27", "bgColor": "#f30d31", "textColor": "#202020", "accentColor": "#ffffff"}], "games": [{"id": 2024020890, "season": 20242025, "gameType": 2, "gameDate": "2025-02-09", "venue": {"default": "Capital One Arena"}, "startTimeUTC": "2025-02-09T17:30:00Z", "easternUTCOffset": "-05:00", "venueUTCOffset": "-05:00", "tvBroadcasts": [{"id": 282, "market": "N", "countryCode": "CA", "network": "SN", "sequenceNumber": 107}, {"id": 558, "market": "A", "countryCode": "US", "network": "Utah16", "sequenceNumber": 381}, {"id": 517, "market": "H", "countryCode": "US", "network": "MNMT", "sequenceNumber": 396}], "gameState": "OFF", "gameScheduleState": "OK", "awayTeam": {"id": 59, "name": {"default": "Utah Hockey Club", "fr": "Club de hockey de l'Utah"}, "abbrev": "UTA", "score": 5, "sog": 27, "logo": "https://assets.nhle.com/logos/nhl/svg/UTA_20242025-20242025_light.svg"}, "homeTeam": {"id": 15, "name": {"default": "Capitals"}, "abbrev": "WSH", "score": 4, "sog": 42, "logo": "https://assets.nhle.com/logos/nhl/svg/WSH_secondary_light.svg"}, "gameCenterLink": "/gamecenter/uta-vs-wsh/2025/02/09/2024020890", "threeMinRecap": "/video/uta-at-wsh-recap-6368568011112", "clock": {"timeRemaining": "00:00", "secondsRemaining": 0, "running": false, "inIntermission": false}, "neutralSite": false, "venueTimezone": "US/Eastern", "period": 5, "periodDescriptor": {"number": 5, "periodType": "SO", "maxRegulationPeriods": 3}, "gameOutcome": {"lastPeriodType": "SO"}, "goals": [{"period": 1, "periodDescriptor": {"number": 1, "periodType": "REG", "maxRegulationPeriods": 3}, "timeInPeriod": "01:10", "playerId": 8482659, "name": {"default": "J. Doan"}, "firstName": {"default": "Josh"}, "lastName": {"default": "Doan"}, "goalModifier": "none", "assists": [{"playerId": 8480855, "name": {"default": "J. McBain"}, "assistsToDate": 6}, {"playerId": 8478971, "name": {"default": "C. Ingram"}, "assistsToDate": 2}], "mugshot": "https://assets.nhle.com/mugs/nhl/20242025/UTA/8482659.png", "teamAbbrev": "UTA", "goalsToDate": 4, "awayScore": 1, "homeScore": 0, "strength": "ev", "highlightClipSharingUrl": "https://nhl.com/video/uta-wsh-doan-scores-goal-against-logan-thompson-6368562139112", "highlightClipSharingUrlFr": "https://nhl.com/fr/video/uta-wsh-doan-marque-un-but-contre-logan-thompson-6368561258112", "highlightClip": 6368562139112, "highlightClipFr": 6368561258112, "discreteClip": 6368562630112, "discreteClipFr": 6368562534112}, {"period": 1, "periodDescriptor": {"number": 1, "periodType": "REG", "maxRegulationPeriods": 3}, "timeInPeriod": "01:42", "playerId": 8479619, "name": {"default": "M. Carcone"}, "firstName": {"default": "Michael"}, "lastName": {"default": "Carcone"}, "goalModifier": "none", "assists": [{"playerId": 8482699, "name": {"default": "D. Guenther"}, "assistsToDate": 21}, {"playerId": 8480084, "name": {"default": "N. DeSimone"}, "assistsToDate": 4}], "mugshot": "https://assets.nhle.com/mugs/nhl/20242025/UTA/8479619.png", "teamAbbrev": "UTA", "goalsToDate": 5, "awayScore": 2, "homeScore": 0, "strength": "ev", "highlightClipSharingUrl": "https://nhl.com/video/uta-wsh-carcone-scores-goal-against-logan-thompson-6368562147112", "highlightClipSharingUrlFr": "https://nhl.com/fr/video/uta-wsh-carcone-marque-un-but-contre-logan-thompson-6368562241112", "highlightClip": 6368562147112, "highlightClipFr": 6368562241112, "discreteClip": 6368564595112, "discreteClipFr": 6368562741112}, {"period": 1, "periodDescriptor": {"number": 1, "periodType": "REG", "maxRegulationPeriods": 3}, "timeInPeriod": "03:47", "playerId": 8476880, "name": {"default": "T. Wilson"}, "firstName": {"default": "Tom"}, "lastName": {"default": "Wilson"}, "goalModifier": "none", "assists": [{"playerId": 8479400, "name": {"default": "P. Dubois"}, "assistsToDate": 31}, {"playerId": 8478440, "name": {"default": "D. Strome"}, "assistsToDate": 38}], "mugshot": "https://assets.nhle.com/mugs/nhl/20242025/WSH/8476880.png", "teamAbbrev": "WSH", "goalsToDate": 23, "awayScore": 2, "homeScore": 1, "strength": "pp", "highlightClipSharingUrl": "https://nhl.com/video/uta-wsh-wilson-scores-ppg-against-connor-ingram-6368563530112", "highlightClipSharingUrlFr": "https://nhl.com/fr/video/uta-wsh-wilson-marque-un-but-en-a-n-contre-connor-ingram-6368563247112", "highlightClip": 6368563530112, "highlightClipFr": 6368563247112, "discreteClip": 6368562447112, "discreteClipFr": 6368564597112}, {"period": 1, "periodDescriptor": {"number": 1, "periodType": "REG", "maxRegulationPeriods": 3}, "timeInPeriod": "07:07", "playerId": 8480855, "name": {"default": "J. McBain"}, "firstName": {"default": "Jack"}, "lastName": {"default": "McBain"}, "goalModifier": "none", "assists": [{"playerId": 8480891, "name": {"default": "M. Kesselring"}, "assistsToDate": 16}, {"playerId": 8482659, "name": {"default": "J. Doan"}, "assistsToDate": 5}], "mugshot": "https://assets.nhle.com/mugs/nhl/20242025/UTA/8480855.png", "teamAbbrev": "UTA", "goalsToDate": 11, "awayScore": 3, "homeScore": 1, "strength": "ev", "highlightClipSharingUrl": "https://nhl.com/video/uta-wsh-mcbain-scores-goal-against-logan-thompson-6368564706112", "highlightClipSharingUrlFr": "https://nhl.com/fr/video/uta-wsh-mcbain-marque-un-but-contre-logan-thompson-6368562651112", "highlightClip": 6368564706112, "highlightClipFr": 6368562651112, "discreteClip": 6368564505112, "discreteClipFr": 6368564705112}, {"period": 1, "periodDescriptor": {"number": 1, "periodType": "REG", "maxRegulationPeriods": 3}, "timeInPeriod": "12:38", "playerId": 8479400, "name": {"default": "P. Dubois"}, "firstName": {"default": "Pierre-Luc"}, "lastName": {"default": "Dubois"}, "goalModifier": "none", "assists": [{"playerId": 8476880, "name": {"default": "T. Wilson"}, "assistsToDate": 18}, {"playerId": 8471214, "name": {"default": "A. Ovechkin", "cs": "A. Ove\u010dkin", "fi": "A. Ovetshkin", "sk": "A. Ove\u010dkin"}, "assistsToDate": 15}], "mugshot": "https://assets.nhle.com/mugs/nhl/20242025/WSH/8479400.png", "teamAbbrev": "WSH", "goalsToDate": 13, "awayScore": 3, "homeScore": 2, "strength": "pp", "highlightClipSharingUrl": "https://nhl.com/video/uta-wsh-dubois-scores-ppg-against-connor-ingram-6368565404112", "highlightClipSharingUrlFr": "https://nhl.com/fr/video/uta-wsh-dubois-marque-un-but-en-a-n-contre-connor-ingram-6368565405112", "highlightClip": 6368565404112, "highlightClipFr": 6368565405112, "discreteClip": 6368565100112, "discreteClipFr": 6368564040112}, {"period": 2, "periodDescriptor": {"number": 2, "periodType": "REG", "maxRegulationPeriods": 3}, "timeInPeriod": "02:47", "playerId": 8482699, "name": {"default": "D. Guenther"}, "firstName": {"default": "Dylan"}, "lastName": {"default": "Guenther"}, "goalModifier": "none", "assists": [{"playerId": 8479343, "name": {"default": "C. Keller"}, "assistsToDate": 40}, {"playerId": 8479410, "name": {"default": "M. Sergachev", "cs": "M. Serga\u010dov", "fi": "M. Sergatshov", "sk": "M. Serga\u010dov"}, "assistsToDate": 26}], "mugshot": "https://assets.nhle.com/mugs/nhl/20242025/UTA/8482699.png", "teamAbbrev": "UTA", "goalsToDate": 20, "awayScore": 4, "homeScore": 2, "strength": "pp", "highlightClipSharingUrl": "https://nhl.com/video/uta-wsh-guenther-scores-goal-against-logan-thompson-6368564373112", "highlightClipSharingUrlFr": "https://nhl.com/fr/video/uta-wsh-guenther-marque-un-but-contre-logan-thompson-6368565828112", "highlightClip": 6368564373112, "highlightClipFr": 6368565828112, "discreteClip": 6368564374112, "discreteClipFr": 6368563886112}, {"period": 3, "periodDescriptor": {"number": 3, "periodType": "REG", "maxRegulationPeriods": 3}, "timeInPeriod": "04:49", "playerId": 8478440, "name": {"default": "D. Strome"}, "firstName": {"default": "Dylan"}, "lastName": {"default": "Strome"}, "goalModifier": "none", "assists": [{"playerId": 8471214, "name": {"default": "A. Ovechkin", "cs": "A. Ove\u010dkin", "fi": "A. Ovetshkin", "sk": "A. Ove\u010dkin"}, "assistsToDate": 16}, {"playerId": 8481580, "name": {"default": "C. McMichael"}, "assistsToDate": 22}], "mugshot": "https://assets.nhle.com/mugs/nhl/20242025/WSH/8478440.png", "teamAbbrev": "WSH", "goalsToDate": 16, "awayScore": 4, "homeScore": 3, "strength": "ev", "highlightClipSharingUrl": "https://nhl.com/video/uta-wsh-strome-scores-goal-against-karel-vejmelka-6368566814112", "highlightClip": 6368566814112, "discreteClip": 6368566799112, "discreteClipFr": 6368568648112}, {"period": 3, "periodDescriptor": {"number": 3, "periodType": "REG", "maxRegulationPeriods": 3}, "timeInPeriod": "18:29", "playerId": 8476880, "name": {"default": "T. Wilson"}, "firstName": {"default": "Tom"}, "lastName": {"default": "Wilson"}, "goalModifier": "none", "assists": [{"playerId": 8471214, "name": {"default": "A. Ovechkin", "cs": "A. Ove\u010dkin", "fi": "A. Ovetshkin", "sk": "A. Ove\u010dkin"}, "assistsToDate": 17}, {"playerId": 8474590, "name": {"default": "J. Carlson"}, "assistsToDate": 31}], "mugshot": "https://assets.nhle.com/mugs/nhl/20242025/WSH/8476880.png", "teamAbbrev": "WSH", "goalsToDate": 24, "awayScore": 4, "homeScore": 4, "strength": "ev", "highlightClipSharingUrl": "https://nhl.com/video/uta-wsh-wilson-scores-goal-against-karel-vejmelka-6368569180112", "highlightClipSharingUrlFr": "https://nhl.com/fr/video/uta-wsh-wilson-marque-un-but-contre-karel-vejmelka-6368569568112", "highlightClip": 6368569180112, "highlightClipFr": 6368569568112, "discreteClip": 6368568094112, "discreteClipFr": 6368569074112}, {"period": 5, "periodDescriptor": {"number": 5, "periodType": "SO", "maxRegulationPeriods": 3}, "timeInPeriod": "00:00", "playerId": 8477951, "name": {"default": "N. Schmaltz"}, "firstName": {"default": "Nick"}, "lastName": {"default": "Schmaltz"}, "goalModifier": "none", "assists": [], "mugshot": "https://assets.nhle.com/mugs/nhl/20242025/UTA/8477951.png", "teamAbbrev": "UTA", "awayScore": 5, "homeScore": 4, "strength": "ev"}]}, {"id": 2024020891, "season": 20242025, "gameType": 2, "gameDate": "2025-02-09", "venue": {"default": "Centre Bell"}, "startTimeUTC": "2025-02-09T18:00:00Z", "easternUTCOffset": "-05:00", "venueUTCOffset": "-05:00", "tvBroadcasts": [{"id": 324, "market": "N", "countryCode": "US", "network": "NHLN", "sequenceNumber": 35}, {"id": 131, "market": "H", "countryCode": "CA", "network": "TSN2", "sequenceNumber": 112}, {"id": 33, "market": "H", "countryCode": "CA", "network": "RDS", "sequenceNumber": 145}, {"id": 560, "market": "A", "countryCode": "US", "network": "FDSNSUN", "sequenceNumber": 287}], "gameState": "OFF", "gameScheduleState": "OK", "awayTeam": {"id": 14, "name": {"default": "Lightning"}, "abbrev": "TBL", "score": 5, "sog": 21, "logo": "https://assets.nhle.com/logos/nhl/svg/TBL_light.svg"}, "homeTeam": {"id": 8, "name": {"default": "Canadiens"}, "abbrev": "MTL", "score": 3, "sog": 35, "logo": "https://assets.nhle.com/logos/nhl/svg/MTL_light.svg"}, "gameCenterLink": "/gamecenter/tbl-vs-mtl/2025/02/09/2024020891", "threeMinRecap": "/video/tbl-at-mtl-recap-6368571666112", "threeMinRecapFr": "/fr/video/tbl-vs-mtl-09-02-2025-resume-6368569404112", "condensedGame": "/video/tbl-at-mtl-condensed-game-6368571166112", "condensedGameFr": "/fr/video/match-condense-lightning-canadiens09-02-2025-6368571475112", "clock": {"timeRemaining": "00:00", "secondsRemaining": 0, "running": false, "inIntermission": false}, "neutralSite": false, "venueTimezone": "America/Montreal", "period": 3, "periodDescriptor": {"number": 3, "periodType": "REG", "maxRegulationPeriods": 3}, "gameOutcome": {"lastPeriodType": "REG"}, "goals": [{"period": 1, "periodDescriptor": {"number": 1, "periodType": "REG", "maxRegulationPeriods": 3}, "timeInPeriod": "06:56", "playerId": 8477426, "name": {"default": "N. Paul"}, "firstName": {"default": "Nick"}, "lastName": {"default": "Paul"}, "goalModifier": "none", "assists": [{"playerId": 8479542, "name": {"default": "B. Hagel"}, "assistsToDate": 35}], "mugshot": "https://assets.nhle.com/mugs/nhl/20242025/TBL/8477426.png", "teamAbbrev": "TBL", "goalsToDate": 16, "awayScore": 1, "homeScore": 0, "strength": "ev", "highlightClipSharingUrl": "https://nhl.com/video/nicholas-paul-with-a-goal-vs-montreal-canadiens-6368565306112", "highlightClipSharingUrlFr": "https://nhl.com/fr/video/tbl-mtl-paul-marque-un-but-contre-jakub-dobes-6368562871112", "highlightClip": 6368565306112, "highlightClipFr": 6368562871112, "discreteClip": 6368564437112, "discreteClipFr": 6368563859112}, {"period": 1, "periodDescriptor": {"number": 1, "periodType": "REG", "maxRegulationPeriods": 3}, "timeInPeriod": "10:28", "playerId": 8475167, "name": {"default": "V. Hedman"}, "firstName": {"default": "Victor"}, "lastName": {"default": "Hedman"}, "goalModifier": "none", "assists": [{"playerId": 8482201, "name": {"default": "G. Goncalves"}, "assistsToDate": 6}, {"playerId": 8478519, "name": {"default": "A. Cirelli"}, "assistsToDate": 22}], "mugshot": "https://assets.nhle.com/mugs/nhl/20242025/TBL/8475167.png", "teamAbbrev": "TBL", "goalsToDate": 8, "awayScore": 2, "homeScore": 0, "strength": "ev", "highlightClipSharingUrl": "https://nhl.com/video/tbl-mtl-hedman-scores-goal-against-jakub-dobes-6368562875112", "highlightClipSharingUrlFr": "https://nhl.com/fr/video/tbl-mtl-hedman-marque-un-but-contre-jakub-dobes-6368563474112", "highlightClip": 6368562875112, "highlightClipFr": 6368563474112, "discreteClip": 6368563572112, "discreteClipFr": 6368563168112}, {"period": 1, "periodDescriptor": {"number": 1, "periodType": "REG", "maxRegulationPeriods": 3}, "timeInPeriod": "18:53", "playerId": 8475848, "name": {"default": "B. Gallagher"}, "firstName": {"default": "Brendan"}, "lastName": {"default": "Gallagher"}, "goalModifier": "none", "assists": [{"playerId": 8481618, "name": {"default": "A. Newhook"}, "assistsToDate": 8}, {"playerId": 8476875, "name": {"default": "M. Matheson"}, "assistsToDate": 21}], "mugshot": "https://assets.nhle.com/mugs/nhl/20242025/MTL/8475848.png", "teamAbbrev": "MTL", "goalsToDate": 13, "awayScore": 2, "homeScore": 1, "strength": "pp", "highlightClipSharingUrl": "https://nhl.com/video/tbl-mtl-gallagher-scores-ppg-against-andrei-vasilevskiy-6368565628112", "highlightClipSharingUrlFr": "https://nhl.com/fr/video/tbl-mtl-gallagher-marque-un-but-en-a-n-contre-andrei-vasilevskiy-6368566127112", "highlightClip": 6368565628112, "highlightClipFr": 6368566127112, "discreteClip": 6368566526112, "discreteClipFr": 6368565255112}, {"period": 2, "periodDescriptor": {"number": 2, "periodType": "REG", "maxRegulationPeriods": 3}, "timeInPeriod": "01:05", "playerId": 8478010, "name": {"default": "B. Point"}, "firstName": {"default": "Brayden"}, "lastName": {"default": "Point"}, "goalModifier": "none", "assists": [{"playerId": 8477404, "name": {"default": "J. Guentzel"}, "assistsToDate": 26}, {"playerId": 8475167, "name": {"default": "V. Hedman"}, "assistsToDate": 36}], "mugshot": "https://assets.nhle.com/mugs/nhl/20242025/TBL/8478010.png", "teamAbbrev": "TBL", "goalsToDate": 31, "awayScore": 3, "homeScore": 1, "strength": "pp", "highlightClipSharingUrl": "https://nhl.com/video/tbl-mtl-point-scores-ppg-against-jakub-dobes-6368566846112", "highlightClipSharingUrlFr": "https://nhl.com/fr/video/tbl-mtl-point-marque-un-but-en-a-n-contre-jakub-dobes-6368565373112", "highlightClip": 6368566846112, "highlightClipFr": 6368565373112, "discreteClip": 6368566646112, "discreteClipFr": 6368565452112}, {"period": 2, "periodDescriptor": {"number": 2, "periodType": "REG", "maxRegulationPeriods": 3}, "timeInPeriod": "06:43", "playerId": 8476878, "name": {"default": "Z. Girgensons"}, "firstName": {"default": "Zemgus"}, "lastName": {"default": "Girgensons"}, "goalModifier": "none", "assists": [{"playerId": 8474715, "name": {"default": "C. Atkinson"}, "assistsToDate": 4}, {"playerId": 8479591, "name": {"default": "M. Eyssimont"}, "assistsToDate": 4}], "mugshot": "https://assets.nhle.com/mugs/nhl/20242025/TBL/8476878.png", "teamAbbrev": "TBL", "goalsToDate": 1, "awayScore": 4, "homeScore": 1, "strength": "ev", "highlightClipSharingUrl": "https://nhl.com/video/tbl-mtl-girgensons-scores-goal-against-samuel-montembeault-6368565783112", "highlightClipSharingUrlFr": "https://nhl.com/fr/video/tbl-mtl-girgensons-marque-un-but-contre-samuel-montembeault-6368565694112", "highlightClip": 6368565783112, "highlightClipFr": 6368565694112, "discreteClip": 6368566468112, "discreteClipFr": 6368567539112}, {"period": 2, "periodDescriptor": {"number": 2, "periodType": "REG", "maxRegulationPeriods": 3}, "timeInPeriod": "12:45", "playerId": 8477989, "name": {"default": "C. Dvorak"}, "firstName": {"default": "Christian"}, "lastName": {"default": "Dvorak"}, "goalModifier": "none", "assists": [{"playerId": 8475233, "name": {"default": "D. Savard"}, "assistsToDate": 10}, {"playerId": 8483515, "name": {"default": "J. Slafkovsk\u00fd"}, "assistsToDate": 22}], "mugshot": "https://assets.nhle.com/mugs/nhl/20242025/MTL/8477989.png", "teamAbbrev": "MTL", "goalsToDate": 6, "awayScore": 4, "homeScore": 2, "strength": "ev", "highlightClipSharingUrl": "https://nhl.com/video/tbl-mtl-dvorak-scores-goal-against-andrei-vasilevskiy-6368566391112", "highlightClipSharingUrlFr": "https://nhl.com/fr/video/tbl-mtl-dvorak-marque-un-but-contre-andrei-vasilevskiy-6368567553112", "highlightClip": 6368566391112, "highlightClipFr": 6368567553112, "discreteClip": 6368565796112, "discreteClipFr": 6368567454112}, {"period": 3, "periodDescriptor": {"number": 3, "periodType": "REG", "maxRegulationPeriods": 3}, "timeInPeriod": "09:19", "playerId": 8475848, "name": {"default": "B. Gallagher"}, "firstName": {"default": "Brendan"}, "lastName": {"default": "Gallagher"}, "goalModifier": "none", "assists": [], "mugshot": "https://assets.nhle.com/mugs/nhl/20242025/MTL/8475848.png", "teamAbbrev": "MTL", "goalsToDate": 14, "awayScore": 4, "homeScore": 3, "strength": "ev", "highlightClipSharingUrl": "https://nhl.com/video/tbl-mtl-gallagher-scores-goal-against-andrei-vasilevskiy-6368568505112", "highlightClipSharingUrlFr": "https://nhl.com/fr/video/tbl-mtl-gallagher-marque-un-but-contre-andrei-vasilevskiy-6368568412112", "highlightClip": 6368568505112, "highlightClipFr": 6368568412112, "discreteClip": 6368570259112, "discreteClipFr": 6368570070112}, {"period": 3, "periodDescriptor": {"number": 3, "periodType": "REG", "maxRegulationPeriods": 3}, "timeInPeriod": "19:44", "playerId": 8478519, "name": {"default": "A. Cirelli"}, "firstName": {"default": "Anthony"}, "lastName": {"default": "Cirelli"}, "goalModifier": "empty-net", "assists": [{"playerId": 8477404, "name": {"default": "J. Guentzel"}, "assistsToDate": 27}, {"playerId": 8479542, "name": {"default": "B. Hagel"}, "assistsToDate": 36}], "mugshot": "https://assets.nhle.com/mugs/nhl/20242025/TBL/8478519.png", "teamAbbrev": "TBL", "goalsToDate": 20, "awayScore": 5, "homeScore": 3, "strength": "ev", "highlightClipSharingUrl": "https://nhl.com/video/tbl-mtl-cirelli-scores-empty-net-goal-6368569690112", "highlightClipSharingUrlFr": "https://nhl.com/fr/video/anthony-cirelli-with-a-goal-vs-les-canadiens-de-montreal-6368569907112", "highlightClip": 6368569690112, "highlightClipFr": 6368569907112, "discreteClip": 6368570576112, "discreteClipFr": 6368569009112}]}]}}